Workbook

Sheet Cover
B7: Patient Insights Support - Ticket Overview
B8: Tickets opened with the Pfizer Support team. The purpose of this document is to present an aggregate view of tickets.
B10: Assignment Group: | D10: GBL-C4 MARM PATIENT INSIGHTS SUPPORT & GBL-C4 MARM PATIENT INIGHTS SUPPORT L3
B11: Document Owners: | D11: Robert Peng
B12: Last updated: | D12: Jan/31/2025

Sheet SLA Config
B2: Priority | C2: Resolve SLA
B3: 1 - Critical | C3: 3
B4: 2 - High | C4: 5
B5: 3 - Medium | C5: 15
B6: 4 - Low | C6: 25

Sheet Incidents
A1: Ticket ID | B1: Opened On | C1: Closed On | D1: Status | E1: Assignee | F1: Age (days) | G1: Application Affected | H1: Brief Description | I1: Category | J1: Subcategory | K1: Reporter | L1: Reported By | M1: Priority | N1: SLA Threshold | O1: SLAs Met?
A2: IM44979703 | B2: 45588 | C2: 45598 | D2: Closed | E2: ANANDA40 | F2: =IF(ISBLANK(C2), NETWORKDAYS(B2,TODAY()), NETWORKDAYS(B2,C2)) -> 8 | G2: PASSPORT | H2: Patient Insights | Job (BHVN HUB) not working in DEV | I2: Batch | J2: IICS | K2: GUNDANNA, PUNYA | L2: Support | M2: =VLOOKUP(Incidents[[#This Row],[Ticket ID]],[1]Incidents!$A$2:$D$792,4,FALSE) -> 4 - Low | N2: =VLOOKUP(Incidents[[#This Row],[Priority]],'SLA Config'!$B$3:$C$6,2,FALSE) -> 25 | O2: =IF(Incidents[[#This Row],[Age (days)]]>Incidents[[#This Row],[SLA Threshold]],"NO","Yes") -> Yes
A3: IM44987477 | B3: 45590 | C3: 45598 | D3: Closed | E3: MALLIA04 | F3: =IF(ISBLANK(C3), NETWORKDAYS(B3,TODAY()), NETWORKDAYS(B3,C3)) -> 6 | G3: PASSPORT | H3: TABLEAU | UAT | FW: PIN_SFLK_PATIENT_SUMMARY_AGG_VW Extract Refresh Failed | I3: Batch | J3: Tableau | K3: MALLIKARJUN INGALALLI, ANUPAMA | L3: Support | M3: =VLOOKUP(Incidents[[#This Row],[Ticket ID]],[1]Incidents!$A$2:$D$792,4,FALSE) -> 4 - Low | N3: =VLOOKUP(Incidents[[#This Row],[Priority]],'SLA Config'!$B$3:$C$6,2,FALSE) -> 25 | O3: =IF(Incidents[[#This Row],[Age (days)]]>Incidents[[#This Row],[SLA Threshold]],"NO","Yes") -> Yes
A4: IM44906264 | B4: 45566 | C4: 45572 | D4: Closed | E4: MALLIA04 | F4: =IF(ISBLANK(C4), NETWORKDAYS(B4,TODAY()), NETWORKDAYS(B4,C4)) -> 5 | G4: PASSPORT | H4: Patient Insights | Master Load failed on 9/29 | I4: Batch | J4: IICS | K4: DINALIS, KONSTANTINOS | L4: Support | M4: =VLOOKUP(Incidents[[#This Row],[Ticket ID]],[1]Incidents!$A$2:$D$792,4,FALSE) -> 2 - High | N4: =VLOOKUP(Incidents[[#This Row],[Priority]],'SLA Config'!$B$3:$C$6,2,FALSE) -> 5 | O4: =IF(Incidents[[#This Row],[Age (days)]]>Incidents[[#This Row],[SLA Threshold]],"NO","Yes") -> Yes
A5: IM44922833 | B5: 45572 | C5: 45577 | D5: Closed | E5: GUNDAP04 | F5: =IF(ISBLANK(C5), NETWORKDAYS(B5,TODAY()), NETWORKDAYS(B5,C5)) -> 5 | G5: PASSPORT | H5: Patient Insights | TF_FAL_PAC_LOAD failed 10/4 | I5: Batch | J5: IICS | K5: DINALIS, KONSTANTINOS | L5: Support | M5: =VLOOKUP(Incidents[[#This Row],[Ticket ID]],[1]Incidents!$A$2:$D$792,4,FALSE) -> 2 - High | N5: =VLOOKUP(Incidents[[#This Row],[Priority]],'SLA Config'!$B$3:$C$6,2,FALSE) -> 5 | O5: =IF(Incidents[[#This Row],[Age (days)]]>Incidents[[#This Row],[SLA Threshold]],"NO","Yes") -> Yes
A6: IM44906241 | B6: 45566 | C6: 45571 | D6: Closed | E6: MALLIA04 | F6: =IF(ISBLANK(C6), NETWORKDAYS(B6,TODAY()), NETWORKDAYS(B6,C6)) -> 4 | G6: PASSPORT | H6: Patient Insights | Taskflow Prescriber Writer load failed on 9/23 | I6: Batch | J6: IICS | K6: DINALIS, KONSTANTINOS | L6: Support | M6: =VLOOKUP(Incidents[[#This Row],[Ticket ID]],[1]Incidents!$A$2:$D$792,4,FALSE) -> 3 - Medium | N6: =VLOOKUP(Incidents[[#This Row],[Priority]],'SLA Config'!$B$3:$C$6,2,FALSE) -> 15 | O6: =IF(Incidents[[#This Row],[Age (days)]]>Incidents[[#This Row],[SLA Threshold]],"NO","Yes") -> Yes
A7: IM44906286 | B7: 45566 | C7: 45571 | D7: Closed | E7: GUNDAP04 | F7: =IF(ISBLANK(C7), NETWORKDAYS(B7,TODAY()), NETWORKDAYS(B7,C7)) -> 4 | G7: CHAMP | H7: Patient Insights | CHAMP Taskflow failed on 9/30 | I7: Batch | J7: IICS | K7: DINALIS, KONSTANTINOS | L7: Support | M7: =VLOOKUP(Incidents[[#This Row],[Ticket ID]],[1]Incidents!$A$2:$D$792,4,FALSE) -> 2 - High | N7: =VLOOKUP(Incidents[[#This Row],[Priority]],'SLA Config'!$B$3:$C$6,2,FALSE) -> 5 | O7: =IF(Incidents[[#This Row],[Age (days)]]>Incidents[[#This Row],[SLA Threshold]],"NO","Yes") -> Yes
A8: IM41854611 | B8: 44729 | C8: 44758 | D8: Closed | E8: SIRIVV02 | F8: =IF(ISBLANK(C8), NETWORKDAYS(B8,TODAY()), NETWORKDAYS(B8,C8)) -> 21 | G8: PASSPORT | H8: The Mapping Task mt_pi_trn_trn_performance_summary_volume_update_data_load failed. | I8: Batch | J8: IICS | K8: SIRIVELLA, VISHNU VARDHAN | L8: Support | M8: =VLOOKUP(Incidents[[#This Row],[Ticket ID]],[1]Incidents!$A$2:$D$792,4,FALSE) -> 3 - Medium | N8: =VLOOKUP(Incidents[[#This Row],[Priority]],'SLA Config'!$B$3:$C$6,2,FALSE) -> 15 | O8: =IF(Incidents[[#This Row],[Age (days)]]>Incidents[[#This Row],[SLA Threshold]],"NO","Yes") -> NO
A9: IM44625661 | B9: 45482 | C9: 45507 | D9: Closed | E9: ANANDA40 | F9: =IF(ISBLANK(C9), NETWORKDAYS(B9,TODAY()), NETWORKDAYS(B9,C9)) -> 19 | G9: PASSPORT | H9: Patient Insights | Automatic Tableau data source refresh failure through IICS | I9: Batch | J9: Tableau | K9: DINALIS, KONSTANTINOS | L9: Support | M9: =VLOOKUP(Incidents[[#This Row],[Ticket ID]],[1]Incidents!$A$2:$D$792,4,FALSE) -> 3 - Medium | N9: =VLOOKUP(Incidents[[#This Row],[Priority]],'SLA Config'!$B$3:$C$6,2,FALSE) -> 15 | O9: =IF(Incidents[[#This Row],[Age (days)]]>Incidents[[#This Row],[SLA Threshold]],"NO","Yes") -> NO
A10: IM41861471 | B10: 44732 | C10: 44754 | D10: Closed | E10: MALLIA04 | F10: =IF(ISBLANK(C10), NETWORKDAYS(B10,TODAY()), NETWORKDAYS(B10,C10)) -> 17 | G10: CHAMP | H10: Rider script issue in Dev server for Patient Insight Application | I10: Batch | J10: Rider Script | K10: MALLIKARJUN INGALALLI, ANUPAMA | L10: Support | M10: =VLOOKUP(Incidents[[#This Row],[Ticket ID]],[1]Incidents!$A$2:$D$792,4,FALSE) -> 4 - Low | N10: =VLOOKUP(Incidents[[#This Row],[Priority]],'SLA Config'!$B$3:$C$6,2,FALSE) -> 25 | O10: =IF(Incidents[[#This Row],[Age (days)]]>Incidents[[#This Row],[SLA Threshold]],"NO","Yes") -> Yes
A11: IM42533854 | B11: 44893 | C11: 44913 | D11: Closed | E11: SIRIVV02 | F11: =IF(ISBLANK(C11), NETWORKDAYS(B11,TODAY()), NETWORKDAYS(B11,C11)) -> 15 | G11: PASSPORT | H11: Mapping task mt_pi_stg_trn_ptnt_dim_data_load in passport workflow getting hanged due to memory sort issues | I11: Batch | J11: Job Failure | K11: DINALIS, KONSTANTINOS | L11: Support | M11: =VLOOKUP(Incidents[[#This Row],[Ticket ID]],[1]Incidents!$A$2:$D$792,4,FALSE) -> 4 - Low | N11: =VLOOKUP(Incidents[[#This Row],[Priority]],'SLA Config'!$B$3:$C$6,2,FALSE) -> 25 | O11: =IF(Incidents[[#This Row],[Age (days)]]>Incidents[[#This Row],[SLA Threshold]],"NO","Yes") -> Yes
A12: IM43777508 | B12: 45232 | C12: 45249 | D12: Closed | E12: MALLIA04 | F12: =IF(ISBLANK(C12), NETWORKDAYS(B12,TODAY()), NETWORKDAYS(B12,C12)) -> 12 | G12: PASSPORT | H12: Patient Insight Application | TF_MASTER_HUB_PJT_LOAD getting failed from 28/11 | I12: Batch | J12: Job Failure | K12: MALLIKARJUN INGALALLI, ANUPAMA | L12: Support | M12: =VLOOKUP(Incidents[[#This Row],[Ticket ID]],[1]Incidents!$A$2:$D$792,4,FALSE) -> 2 - High | N12: =VLOOKUP(Incidents[[#This Row],[Priority]],'SLA Config'!$B$3:$C$6,2,FALSE) -> 5 | O12: =IF(Incidents[[#This Row],[Age (days)]]>Incidents[[#This Row],[SLA Threshold]],"NO","Yes") -> NO
A13: IM44497164 | B13: 45442 | C13: 45459 | D13: Closed | E13: ANANDA40 | F13: =IF(ISBLANK(C13), NETWORKDAYS(B13,TODAY()), NETWORKDAYS(B13,C13)) -> 12 | G13: PASSPORT | H13: Trigger the TALZENNA Taskflow in UAT environment. | I13: Batch | J13: Ad-hoc job | K13: VEMURI, VISHAL | L13: Digital | M13: =VLOOKUP(Incidents[[#This Row],[Ticket ID]],[1]Incidents!$A$2:$D$792,4,FALSE) -> 4 - Low | N13: =VLOOKUP(Incidents[[#This Row],[Priority]],'SLA Config'!$B$3:$C$6,2,FALSE) -> 25 | O13: =IF(Incidents[[#This Row],[Age (days)]]>Incidents[[#This Row],[SLA Threshold]],"NO","Yes") -> Yes
... A110: IM44368751 | B110: 45405 | C110: 45465 | D110: Closed | E110: ANANDA40 | F110: =IF(ISBLANK(C110), NETWORKDAYS(B110,TODAY()), NETWORKDAYS(B110,C110)) -> 44 | G110: PASSPORT | H110: Patient Insight |Data mismatch for the ACCOUNT, ACCOUNT_TYPE columns in Ibrance, Xeljanz - Persistency Mappings | I110: Data Issue | J110: Snowflake | K110: CHENNAM, VAMSIKRISHNA | L110: Digital | M110: =VLOOKUP(Incidents[[#This Row],[Ticket ID]],[1]Incidents!$A$2:$D$792,4,FALSE) -> 3 - Medium | N110: =VLOOKUP(Incidents[[#This Row],[Priority]],'SLA Config'!$B$3:$C$6,2,FALSE) -> 15 | O110: =IF(Incidents[[#This Row],[Age (days)]]>Incidents[[#This Row],[SLA Threshold]],"NO","Yes") -> NO
A111: IM45111282 | B111: 45629 | C111: 45690 | D111: Closed | E111: ANANDA40 | F111: =IF(ISBLANK(C111), NETWORKDAYS(B111,TODAY()), NETWORKDAYS(B111,C111)) -> 44 | G111: PASSPORT | H111: AMBA data differences between Walgreens and patient insight extraction | I111: Data Issue | K111: GOLDSMITH, GEORGE | M111: =VLOOKUP(Incidents[[#This Row],[Ticket ID]],[1]Incidents!$A$2:$D$792,4,FALSE) -> 3 - Medium | N111: =VLOOKUP(Incidents[[#This Row],[Priority]],'SLA Config'!$B$3:$C$6,2,FALSE) -> 15 | O111: =IF(Incidents[[#This Row],[Age (days)]]>Incidents[[#This Row],[SLA Threshold]],"NO","Yes") -> NO
A112: IM43067170 | B112: 45035 | C112: 45095 | D112: Closed | E112: GANJR04 | F112: =IF(ISBLANK(C112), NETWORKDAYS(B112,TODAY()), NETWORKDAYS(B112,C112)) -> 43 | G112: PASSPORT | H112: Patient Insights - Fulfillment rate and network calculation logic | I112: Data Issue | J112: Tableau | K112: DESAI, RAJ | L112: Business | M112: =VLOOKUP(Incidents[[#This Row],[Ticket ID]],[1]Incidents!$A$2:$D$792,4,FALSE) -> 4 - Low | N112: =VLOOKUP(Incidents[[#This Row],[Priority]],'SLA Config'!$B$3:$C$6,2,FALSE) -> 25 | O112: =IF(Incidents[[#This Row],[Age (days)]]>Incidents[[#This Row],[SLA Threshold]],"NO","Yes") -> NO
A113: IM45135442 | B113: 45637 | C113: 45740 | D113: Closed | E113: MALLIA04 | F113: =IF(ISBLANK(C113), NETWORKDAYS(B113,TODAY()), NETWORKDAYS(B113,C113)) -> 74 | G113: CHAMP | H113: Patient Insights - Data Issue | I113: Data Issue | K113: TROUGHT, ALLISON | L113: Business | M113: =VLOOKUP(Incidents[[#This Row],[Ticket ID]],[1]Incidents!$A$2:$D$792,4,FALSE) -> 3 - Medium | N113: =VLOOKUP(Incidents[[#This Row],[Priority]],'SLA Config'!$B$3:$C$6,2,FALSE) -> 15 | O113: =IF(Incidents[[#This Row],[Age (days)]]>Incidents[[#This Row],[SLA Threshold]],"NO","Yes") -> NO
A114: IM44591811 | B114: 45471 | C114: 45528 | D114: Closed | E114: DINALK01 | F114: =IF(ISBLANK(C114), NETWORKDAYS(B114,TODAY()), NETWORKDAYS(B114,C114)) -> 41 | G114: PASSPORT | H114: Amba Dashboard Data Inquiry | I114: Data Issue | J114: Tableau | K114: ALTER, JONATHAN MICHAEL | L114: Business | M114: =VLOOKUP(Incidents[[#This Row],[Ticket ID]],[1]Incidents!$A$2:$D$792,4,FALSE) -> 4 - Low | N114: =VLOOKUP(Incidents[[#This Row],[Priority]],'SLA Config'!$B$3:$C$6,2,FALSE) -> 25 | O114: =IF(Incidents[[#This Row],[Age (days)]]>Incidents[[#This Row],[SLA Threshold]],"NO","Yes") -> NO
A115: IM43644345 | B115: 45195 | C115: 45249 | D115: Closed | E115: MALLIA04 | F115: =IF(ISBLANK(C115), NETWORKDAYS(B115,TODAY()), NETWORKDAYS(B115,C115)) -> 39 | G115: CHAMP | H115: Patient Insights - DON Services data issue | I115: Data Issue | J115: Web App | K115: TROUGHT, ALLISON | L115: Business | M115: =VLOOKUP(Incidents[[#This Row],[Ticket ID]],[1]Incidents!$A$2:$D$792,4,FALSE) -> 4 - Low | N115: =VLOOKUP(Incidents[[#This Row],[Priority]],'SLA Config'!$B$3:$C$6,2,FALSE) -> 25 | O115: =IF(Incidents[[#This Row],[Age (days)]]>Incidents[[#This Row],[SLA Threshold]],"NO","Yes") -> NO
A116: IM43606214 | B116: 45184 | C116: 45237 | D116: Closed | E116: DINALK01 | F116: =IF(ISBLANK(C116), NETWORKDAYS(B116,TODAY()), NETWORKDAYS(B116,C116)) -> 38 | G116: PASSPORT | H116: Patient Insights | SONEXUS | Triage Data questions | I116: Data Issue | J116: Question | K116: SAMIAYYAN, SHANMUGAM | L116: Digital | M116: =VLOOKUP(Incidents[[#This Row],[Ticket ID]],[1]Incidents!$A$2:$D$792,4,FALSE) -> 4 - Low | N116: =VLOOKUP(Incidents[[#This Row],[Priority]],'SLA Config'!$B$3:$C$6,2,FALSE) -> 25 | O116: =IF(Incidents[[#This Row],[Age (days)]]>Incidents[[#This Row],[SLA Threshold]],"NO","Yes") -> NO
A117: IM44561005 | B117: 45462 | C117: 45514 | D117: Closed | E117: DINALK01 | F117: =IF(ISBLANK(C117), NETWORKDAYS(B117,TODAY()), NETWORKDAYS(B117,C117)) -> 38 | G117: PASSPORT | H117: Patient Insights | DERM | HCO Phone and Fax length issue | I117: Data Issue | J117: Sonexus | K117: SHAIK, SADHATHAMEED | L117: Digital | M117: =VLOOKUP(Incidents[[#This Row],[Ticket ID]],[1]Incidents!$A$2:$D$792,4,FALSE) -> 4 - Low | N117: =VLOOKUP(Incidents[[#This Row],[Priority]],'SLA Config'!$B$3:$C$6,2,FALSE) -> 25 | O117: =IF(Incidents[[#This Row],[Age (days)]]>Incidents[[#This Row],[SLA Threshold]],"NO","Yes") -> NO
A118: IM45135126 | B118: 45637 | C118: 45690 | D118: Closed | E118: ANANDA40 | F118: =IF(ISBLANK(C118), NETWORKDAYS(B118,TODAY()), NETWORKDAYS(B118,C118)) -> 38 | G118: PASSPORT | H118: Patient Insights -FRM Dashboard: Vyndamax data not populating | I118: Data Issue | J118: Tableau | K118: WANG, ERIC | L118: Business | M118: =VLOOKUP(Incidents[[#This Row],[Ticket ID]],[1]Incidents!$A$2:$D$792,4,FALSE) -> 2 - High | N118: =VLOOKUP(Incidents[[#This Row],[Priority]],'SLA Config'!$B$3:$C$6,2,FALSE) -> 5 | O118: =IF(Incidents[[#This Row],[Age (days)]]>Incidents[[#This Row],[SLA Threshold]],"NO","Yes") -> NO
A119: IM44084842 | B119: 45321 | C119: 45371 | D119: Closed | E119: ANANDA40 | F119: =IF(ISBLANK(C119), NETWORKDAYS(B119,TODAY()), NETWORKDAYS(B119,C119)) -> 37 | G119: PASSPORT | H119: Patient Insights | Texas Account Mapping | I119: Data Issue | J119: Tableau | K119: ANAND, ASHISH | L119: Support | M119: =VLOOKUP(Incidents[[#This Row],[Ticket ID]],[1]Incidents!$A$2:$D$792,4,FALSE) -> 4 - Low | N119: =VLOOKUP(Incidents[[#This Row],[Priority]],'SLA Config'!$B$3:$C$6,2,FALSE) -> 25 | O119: =IF(Incidents[[#This Row],[Age (days)]]>Incidents[[#This Row],[SLA Threshold]],"NO","Yes") -> NO
A120: IM44260802 | B120: 45372 | C120: 45423 | D120: Closed | E120: MALLIA04 | F120: =IF(ISBLANK(C120), NETWORKDAYS(B120,TODAY()), NETWORKDAYS(B120,C120)) -> 37 | G120: CHAMP | H120: Patient Insights - CHAMP :missing SPIF for Walgreens Vyndaqel/Vyndamax | I120: Data Issue | J120: Tableau | K120: TROUGHT, ALLISON | L120: Business | M120: =VLOOKUP(Incidents[[#This Row],[Ticket ID]],[1]Incidents!$A$2:$D$792,4,FALSE) -> 2 - High | N120: =VLOOKUP(Incidents[[#This Row],[Priority]],'SLA Config'!$B$3:$C$6,2,FALSE) -> 5 | O120: =IF(Incidents[[#This Row],[Age (days)]]>Incidents[[#This Row],[SLA Threshold]],"NO","Yes") -> NO
A121: IM44838337 | B121: 45545 | C121: 45595 | D121: Closed | E121: MALLIA04 | F121: =IF(ISBLANK(C121), NETWORKDAYS(B121,TODAY()), NETWORKDAYS(B121,C121)) -> 37 | G121: PASSPORT | H121: Patient Insights | Primary_payer_pcn values are populating as null - Patient Summary Load mappings | I121: Data Issue | J121: Tableau | K121: MALLIKARJUN INGALALLI, ANUPAMA | L121: Support | M121: =VLOOKUP(Incidents[[#This Row],[Ticket ID]],[1]Incidents!$A$2:$D$792,4,FALSE) -> 3 - Medium | N121: =VLOOKUP(Incidents[[#This Row],[Priority]],'SLA Config'!$B$3:$C$6,2,FALSE) -> 15 | O121: =IF(Incidents[[#This Row],[Age (days)]]>Incidents[[#This Row],[SLA Threshold]],"NO","Yes") -> NO
A122: IM43606115 | B122: 45184 | C122: 45235 | D122: Closed | E122: DINALK01 | F122: =IF(ISBLANK(C122), NETWORKDAYS(B122,TODAY()), NETWORKDAYS(B122,C122)) -> 36 | G122: PASSPORT | H122: Patient Insights | LASH | Triage Data questions | I122: Data Issue | J122: Question | K122: SAMIAYYAN, SHANMUGAM | L122: Digital | M122: =VLOOKUP(Incidents[[#This Row],[Ticket ID]],[1]Incidents!$A$2:$D$792,4,FALSE) -> 4 - Low | N122: =VLOOKUP(Incidents[[#This Row],[Priority]],'SLA Config'!$B$3:$C$6,2,FALSE) -> 25 | O122: =IF(Incidents[[#This Row],[Age (days)]]>Incidents[[#This Row],[SLA Threshold]],"NO","Yes") -> NO
A123: IM43792481 | B123: 45237 | C123: 45286 | D123: Closed | E123: ANANDA40 | F123: =IF(ISBLANK(C123), NETWORKDAYS(B123,TODAY()), NETWORKDAYS(B123,C123)) -> 36 | G123: CHAMP | H123: Patient Insights - CHAMP SPP Validation - Data Issue | I123: Data Issue | J123: Tableau | K123: TROUGHT, ALLISON | L123: Business | M123: =VLOOKUP(Incidents[[#This Row],[Ticket ID]],[1]Incidents!$A$2:$D$792,4,FALSE) -> 4 - Low | N123: =VLOOKUP(Incidents[[#This Row],[Priority]],'SLA Config'!$B$3:$C$6,2,FALSE) -> 25 | O123: =IF(Incidents[[#This Row],[Age (days)]]>Incidents[[#This Row],[SLA Threshold]],"NO","Yes") -> NO
A124: IM43262030 | B124: 45090 | C124: 45138 | D124: Closed | E124: BABUS32 | F124: =IF(ISBLANK(C124), NETWORKDAYS(B124,TODAY()), NETWORKDAYS(B124,C124)) -> 35 | G124: PASSPORT | H124: Patient Insights - AMBA Dashboard refresh date | I124: Data Issue | J124: Tableau | K124: ALTER, JONATHAN MICHAEL | L124: Business | M124: =VLOOKUP(Incidents[[#This Row],[Ticket ID]],[1]Incidents!$A$2:$D$792,4,FALSE) -> 3 - Medium | N124: =VLOOKUP(Incidents[[#This Row],[Priority]],'SLA Config'!$B$3:$C$6,2,FALSE) -> 15 | O124: =IF(Incidents[[#This Row],[Age (days)]]>Incidents[[#This Row],[SLA Threshold]],"NO","Yes") -> NO
A125: IM43612488 | B125: 45187 | C125: 45235 | D125: Closed | E125: DINALK01 | F125: =IF(ISBLANK(C125), NETWORKDAYS(B125,TODAY()), NETWORKDAYS(B125,C125)) -> 35 | G125: PASSPORT | H125: Patient Insights | LASH | PAC data question | I125: Data Issue | J125: Question | K125: SAMIAYYAN, SHANMUGAM | L125: Digital | M125: =VLOOKUP(Incidents[[#This Row],[Ticket ID]],[1]Incidents!$A$2:$D$792,4,FALSE) -> 4 - Low | N125: =VLOOKUP(Incidents[[#This Row],[Priority]],'SLA Config'!$B$3:$C$6,2,FALSE) -> 25 | O125: =IF(Incidents[[#This Row],[Age (days)]]>Incidents[[#This Row],[SLA Threshold]],"NO","Yes") -> NO
... A179: IM44194762 | B179: 45352 | C179: 45367 | D179: Closed | E179: DINALK01 | F179: =IF(ISBLANK(C179), NETWORKDAYS(B179,TODAY()), NETWORKDAYS(B179,C179)) -> 11 | G179: CHAMP | H179: Patient Insights - champ -Data Issue for Kroger account | I179: Data Issue | J179: Tableau | K179: TROUGHT, ALLISON | L179: Business | M179: =VLOOKUP(Incidents[[#This Row],[Ticket ID]],[1]Incidents!$A$2:$D$792,4,FALSE) -> 4 - Low | N179: =VLOOKUP(Incidents[[#This Row],[Priority]],'SLA Config'!$B$3:$C$6,2,FALSE) -> 25 | O179: =IF(Incidents[[#This Row],[Age (days)]]>Incidents[[#This Row],[SLA Threshold]],"NO","Yes") -> Yes
A180: IM45245485 | B180: 45679 | C180: 45693 | D180: Closed | E180: BABUS32 | F180: =IF(ISBLANK(C180), NETWORKDAYS(B180,TODAY()), NETWORKDAYS(B180,C180)) -> 11 | G180: CHAMP | H180: Patient Insights - Data Issue | I180: Data Issue | K180: TROUGHT, ALLISON | L180: Business | M180: =VLOOKUP(Incidents[[#This Row],[Ticket ID]],[1]Incidents!$A$2:$D$792,4,FALSE) -> 2 - High | N180: =VLOOKUP(Incidents[[#This Row],[Priority]],'SLA Config'!$B$3:$C$6,2,FALSE) -> 5 | O180: =IF(Incidents[[#This Row],[Age (days)]]>Incidents[[#This Row],[SLA Threshold]],"NO","Yes") -> NO
A181: IM45289084 | B181: 45694 | C181: 45703 | D181: Closed | E181: MALLIA04 | F181: =IF(ISBLANK(C181), NETWORKDAYS(B181,TODAY()), NETWORKDAYS(B181,C181)) -> 7 | G181: CHAMP | H181: Patient Insights - Data Issue | I181: Data Issue | K181: TROUGHT, ALLISON | L181: Business | M181: =VLOOKUP(Incidents[[#This Row],[Ticket ID]],[1]Incidents!$A$2:$D$792,4,FALSE) -> 3 - Medium | N181: =VLOOKUP(Incidents[[#This Row],[Priority]],'SLA Config'!$B$3:$C$6,2,FALSE) -> 15 | O181: =IF(Incidents[[#This Row],[Age (days)]]>Incidents[[#This Row],[SLA Threshold]],"NO","Yes") -> Yes
A182: IM45279941 | B182: 45692 | C182: 45699 | D182: Closed | E182: MALLIA04 | F182: =IF(ISBLANK(C182), NETWORKDAYS(B182,TODAY()), NETWORKDAYS(B182,C182)) -> 6 | G182: CHAMP | H182: Plan Payer channel mapping question - FAL | I182: Data Issue | K182: HAQUE, ASAD UL | M182: =VLOOKUP(Incidents[[#This Row],[Ticket ID]],[1]Incidents!$A$2:$D$792,4,FALSE) -> 4 - Low | N182: =VLOOKUP(Incidents[[#This Row],[Priority]],'SLA Config'!$B$3:$C$6,2,FALSE) -> 25 | O182: =IF(Incidents[[#This Row],[Age (days)]]>Incidents[[#This Row],[SLA Threshold]],"NO","Yes") -> Yes
A183: IM42202493 | B183: 44817 | C183: 44830 | D183: Closed | E183: SIRIVV02 | F183: =IF(ISBLANK(C183), NETWORKDAYS(B183,TODAY()), NETWORKDAYS(B183,C183)) -> 10 | G183: PASSPORT | H183: PASSPORT | Metrics for recent quarters are not showing up in the platform. | I183: Data Issue | J183: Tableau | K183: THANGAVEL, RAMESH | L183: Business | M183: =VLOOKUP(Incidents[[#This Row],[Ticket ID]],[1]Incidents!$A$2:$D$792,4,FALSE) -> 3 - Medium | N183: =VLOOKUP(Incidents[[#This Row],[Priority]],'SLA Config'!$B$3:$C$6,2,FALSE) -> 15 | O183: =IF(Incidents[[#This Row],[Age (days)]]>Incidents[[#This Row],[SLA Threshold]],"NO","Yes") -> Yes
A184: IM42202626 | B184: 44817 | C184: 44830 | D184: Closed | E184: SIRIVV02 | F184: =IF(ISBLANK(C184), NETWORKDAYS(B184,TODAY()), NETWORKDAYS(B184,C184)) -> 10 | G184: PASSPORT | H184: Passport | Wrong products getting included in portfolio level reports. | I184: Data Issue | J184: Tableau | K184: THANGAVEL, RAMESH | L184: Business | M184: =VLOOKUP(Incidents[[#This Row],[Ticket ID]],[1]Incidents!$A$2:$D$792,4,FALSE) -> 4 - Low | N184: =VLOOKUP(Incidents[[#This Row],[Priority]],'SLA Config'!$B$3:$C$6,2,FALSE) -> 25 | O184: =IF(Incidents[[#This Row],[Age (days)]]>Incidents[[#This Row],[SLA Threshold]],"NO","Yes") -> Yes
A185: IM42905363 | B185: 44991 | C185: 45003 | D185: Closed | E185: SIRIVV02 | F185: =IF(ISBLANK(C185), NETWORKDAYS(B185,TODAY()), NETWORKDAYS(B185,C185)) -> 10 | G185: CHAMP | H185: Patient Point - Contract 4852 missing start dates | I185: Data Issue | J185: Web App | K185: TROUGHT, ALLISON | L185: Business | M185: =VLOOKUP(Incidents[[#This Row],[Ticket ID]],[1]Incidents!$A$2:$D$792,4,FALSE) -> 4 - Low | N185: =VLOOKUP(Incidents[[#This Row],[Priority]],'SLA Config'!$B$3:$C$6,2,FALSE) -> 25 | O185: =IF(Incidents[[#This Row],[Age (days)]]>Incidents[[#This Row],[SLA Threshold]],"NO","Yes") -> Yes
A186: IM44232550 | B186: 45364 | C186: 45377 | D186: Closed | E186: MALLIA04 | F186: =IF(ISBLANK(C186), NETWORKDAYS(B186,TODAY()), NETWORKDAYS(B186,C186)) -> 10 | G186: CHAMP | H186: IM44232550 - CHAMP is not picking up SPIF for CVS Caremark Vyndaqel program | I186: Data Issue | J186: Tableau | K186: TROUGHT, ALLISON | L186: Business | M186: =VLOOKUP(Incidents[[#This Row],[Ticket ID]],[1]Incidents!$A$2:$D$792,4,FALSE) -> 3 - Medium | N186: =VLOOKUP(Incidents[[#This Row],[Priority]],'SLA Config'!$B$3:$C$6,2,FALSE) -> 15 | O186: =IF(Incidents[[#This Row],[Age (days)]]>Incidents[[#This Row],[SLA Threshold]],"NO","Yes") -> Yes
A187: IM44559176 | B187: 45461 | C187: 45474 | D187: Closed | E187: MALLIA04 | F187: =IF(ISBLANK(C187), NETWORKDAYS(B187,TODAY()), NETWORKDAYS(B187,C187)) -> 10 | G187: CHAMP | H187: Patient Insights - Optum/Somavert Welcome Calls - November 2023 mismatch | I187: Data Issue | J187: Tableau | K187: TROUGHT, ALLISON | L187: Business | M187: =VLOOKUP(Incidents[[#This Row],[Ticket ID]],[1]Incidents!$A$2:$D$792,4,FALSE) -> 4 - Low | N187: =VLOOKUP(Incidents[[#This Row],[Priority]],'SLA Config'!$B$3:$C$6,2,FALSE) -> 25 | O187: =IF(Incidents[[#This Row],[Age (days)]]>Incidents[[#This Row],[SLA Threshold]],"NO","Yes") -> Yes
A188: IM44643718 | B188: 45488 | C188: 45500 | D188: Closed | E188: DINALK01 | F188: =IF(ISBLANK(C188), NETWORKDAYS(B188,TODAY()), NETWORKDAYS(B188,C188)) -> 10 | G188: PASSPORT | H188: SPP Data Issue for XELJANZ,CIBINQO,LITFULO,VELSIPITY | I188: Data Issue | J188: Tableau | K188: PARAMESWARAN, KARTHIGA | L188: Digital | M188: =VLOOKUP(Incidents[[#This Row],[Ticket ID]],[1]Incidents!$A$2:$D$792,4,FALSE) -> 2 - High | N188: =VLOOKUP(Incidents[[#This Row],[Priority]],'SLA Config'!$B$3:$C$6,2,FALSE) -> 5 | O188: =IF(Incidents[[#This Row],[Age (days)]]>Incidents[[#This Row],[SLA Threshold]],"NO","Yes") -> NO
A189: IM44791815 | B189: 45530 | C189: 45542 | D189: Closed | E189: MALLIA04 | F189: =IF(ISBLANK(C189), NETWORKDAYS(B189,TODAY()), NETWORKDAYS(B189,C189)) -> 10 | G189: CHAMP | H189: Patient Insights - Incorrect missing invoice message for Contract 4879 | I189: Data Issue | J189: Tableau | K189: TROUGHT, ALLISON | L189: Business | M189: =VLOOKUP(Incidents[[#This Row],[Ticket ID]],[1]Incidents!$A$2:$D$792,4,FALSE) -> 3 - Medium | N189: =VLOOKUP(Incidents[[#This Row],[Priority]],'SLA Config'!$B$3:$C$6,2,FALSE) -> 15 | O189: =IF(Incidents[[#This Row],[Age (days)]]>Incidents[[#This Row],[SLA Threshold]],"NO","Yes") -> Yes
A190: IM45128411 | B190: 45635 | C190: 45648 | D190: Closed | E190: GUNDAP04 | F190: =IF(ISBLANK(C190), NETWORKDAYS(B190,TODAY()), NETWORKDAYS(B190,C190)) -> 10 | G190: PASSPORT | H190: Velsipity Acaria-missing data in Passport dashboards | I190: Data Issue | K190: DESAI, RAJ | L190: Business | M190: =VLOOKUP(Incidents[[#This Row],[Ticket ID]],[1]Incidents!$A$2:$D$792,4,FALSE) -> 3 - Medium | N190: =VLOOKUP(Incidents[[#This Row],[Priority]],'SLA Config'!$B$3:$C$6,2,FALSE) -> 15 | O190: =IF(Incidents[[#This Row],[Age (days)]]>Incidents[[#This Row],[SLA Threshold]],"NO","Yes") -> Yes
A191: IM45303177 | B191: 45699 | C191: 45706 | D191: Closed | E191: MALLIA04 | F191: =IF(ISBLANK(C191), NETWORKDAYS(B191,TODAY()), NETWORKDAYS(B191,C191)) -> 6 | G191: CHAMP | H191: Patient Insights - Data Issue | I191: Data Issue | K191: TROUGHT, ALLISON | L191: Business | M191: =VLOOKUP(Incidents[[#This Row],[Ticket ID]],[1]Incidents!$A$2:$D$792,4,FALSE) -> 3 - Medium | N191: =VLOOKUP(Incidents[[#This Row],[Priority]],'SLA Config'!$B$3:$C$6,2,FALSE) -> 15 | O191: =IF(Incidents[[#This Row],[Age (days)]]>Incidents[[#This Row],[SLA Threshold]],"NO","Yes") -> Yes
A192: IM45335600 | B192: 45709 | C192: 45733 | D192: Closed | E192: BABUS32 | F192: =IF(ISBLANK(C192), NETWORKDAYS(B192,TODAY()), NETWORKDAYS(B192,C192)) -> 17 | G192: CHAMP | H192: Patient Insights - Application Issue | I192: Data Issue | K192: TROUGHT, ALLISON | L192: Business | M192: =VLOOKUP(Incidents[[#This Row],[Ticket ID]],[1]Incidents!$A$2:$D$792,4,FALSE) -> 4 - Low | N192: =VLOOKUP(Incidents[[#This Row],[Priority]],'SLA Config'!$B$3:$C$6,2,FALSE) -> 25 | O192: =IF(Incidents[[#This Row],[Age (days)]]>Incidents[[#This Row],[SLA Threshold]],"NO","Yes") -> Yes
A193: IM45096090 | B193: 45623 | C193: 45635 | D193: Closed | E193: MALLIA04 | F193: =IF(ISBLANK(C193), NETWORKDAYS(B193,TODAY()), NETWORKDAYS(B193,C193)) -> 9 | G193: CHAMP | H193: Patient Insights - SPIF mapping issue for Walgreens/Braftovi | I193: Data Issue | J193: Mapping | K193: TROUGHT, ALLISON | L193: Business | M193: =VLOOKUP(Incidents[[#This Row],[Ticket ID]],[1]Incidents!$A$2:$D$792,4,FALSE) -> 4 - Low | N193: =VLOOKUP(Incidents[[#This Row],[Priority]],'SLA Config'!$B$3:$C$6,2,FALSE) -> 25 | O193: =IF(Incidents[[#This Row],[Age (days)]]>Incidents[[#This Row],[SLA Threshold]],"NO","Yes") -> Yes
A194: IM45242042 | B194: 45678 | C194: 45689 | D194: Closed | E194: ANANDA40 | F194: =IF(ISBLANK(C194), NETWORKDAYS(B194,TODAY()), NETWORKDAYS(B194,C194)) -> 9 | G194: CHAMP | H194: Update data for OSOT Dashboard - Route to GBL-C4 MARM PATIENT INSIGHTS SUPPORT | I194: Data Issue | K194: SAMIAYYAN, SHANMUGAM | L194: Digital | M194: =VLOOKUP(Incidents[[#This Row],[Ticket ID]],[1]Incidents!$A$2:$D$792,4,FALSE) -> 2 - High | N194: =VLOOKUP(Incidents[[#This Row],[Priority]],'SLA Config'!$B$3:$C$6,2,FALSE) -> 5 | O194: =IF(Incidents[[#This Row],[Age (days)]]>Incidents[[#This Row],[SLA Threshold]],"NO","Yes") -> NO
A195: IM45342053 | B195: 45712 | C195: 45733 | D195: Closed | E195: ANANDA40 | F195: =IF(ISBLANK(C195), NETWORKDAYS(B195,TODAY()), NETWORKDAYS(B195,C195)) -> 16 | G195: CHAMP | H195: Patient Insights - Data Issue | I195: Data Issue | K195: TROUGHT, ALLISON | L195: Business | M195: =VLOOKUP(Incidents[[#This Row],[Ticket ID]],[1]Incidents!$A$2:$D$792,4,FALSE) -> 3 - Medium | N195: =VLOOKUP(Incidents[[#This Row],[Priority]],'SLA Config'!$B$3:$C$6,2,FALSE) -> 15 | O195: =IF(Incidents[[#This Row],[Age (days)]]>Incidents[[#This Row],[SLA Threshold]],"NO","Yes") -> NO
A196: IM43833579 | B196: 45247 | C196: 45258 | D196: Closed | E196: DINALK01 | F196: =IF(ISBLANK(C196), NETWORKDAYS(B196,TODAY()), NETWORKDAYS(B196,C196)) -> 8 | G196: CHAMP | H196: Patient Insights - CHAMP - BioPlus-Ibrance unmapped records | I196: Data Issue | J196: Tableau | K196: TROUGHT, ALLISON | L196: Business | M196: =VLOOKUP(Incidents[[#This Row],[Ticket ID]],[1]Incidents!$A$2:$D$792,4,FALSE) -> 4 - Low | N196: =VLOOKUP(Incidents[[#This Row],[Priority]],'SLA Config'!$B$3:$C$6,2,FALSE) -> 25 | O196: =IF(Incidents[[#This Row],[Age (days)]]>Incidents[[#This Row],[SLA Threshold]],"NO","Yes") -> Yes
A197: IM44775855 | B197: 45525 | C197: 45535 | D197: Closed | E197: MALLIA04 | F197: =IF(ISBLANK(C197), NETWORKDAYS(B197,TODAY()), NETWORKDAYS(B197,C197)) -> 8 | G197: PASSPORT | H197: Patient Insights | AMBA dashboard duplicate data | I197: Data Issue | J197: Tableau | K197: ALTER, JONATHAN MICHAEL | L197: Business | M197: =VLOOKUP(Incidents[[#This Row],[Ticket ID]],[1]Incidents!$A$2:$D$792,4,FALSE) -> 2 - High | N197: =VLOOKUP(Incidents[[#This Row],[Priority]],'SLA Config'!$B$3:$C$6,2,FALSE) -> 5 | O197: =IF(Incidents[[#This Row],[Age (days)]]>Incidents[[#This Row],[SLA Threshold]],"NO","Yes") -> NO
A198: IM44948319 | B198: 45580 | C198: 45623 | D198: Closed | E198: ANANDA40 | F198: =IF(ISBLANK(C198), NETWORKDAYS(B198,TODAY()), NETWORKDAYS(B198,C198)) -> 32 | G198: PASSPORT | H198: Patient Insights - August Data Point for PA CMM Status in KPI Engagement Report | I198: Data Issue | J198: Tableau | K198: GOLLER, MARK | L198: Business | M198: =VLOOKUP(Incidents[[#This Row],[Ticket ID]],[1]Incidents!$A$2:$D$792,4,FALSE) -> 4 - Low | N198: =VLOOKUP(Incidents[[#This Row],[Priority]],'SLA Config'!$B$3:$C$6,2,FALSE) -> 25 | O198: =IF(Incidents[[#This Row],[Age (days)]]>Incidents[[#This Row],[SLA Threshold]],"NO","Yes") -> NO
A199: IM44960493 | B199: 45583 | C199: 45594 | D199: Closed | E199: ANANDA40 | F199: =IF(ISBLANK(C199), NETWORKDAYS(B199,TODAY()), NETWORKDAYS(B199,C199)) -> 8 | G199: PASSPORT | H199: Patient Insights | Other_Coverage_CD | BHVN COPAY | I199: Data Issue | J199: Claritas | K199: ANAND, ASHISH | L199: Support | M199: =VLOOKUP(Incidents[[#This Row],[Ticket ID]],[1]Incidents!$A$2:$D$792,4,FALSE) -> 4 - Low | N199: =VLOOKUP(Incidents[[#This Row],[Priority]],'SLA Config'!$B$3:$C$6,2,FALSE) -> 25 | O199: =IF(Incidents[[#This Row],[Age (days)]]>Incidents[[#This Row],[SLA Threshold]],"NO","Yes") -> Yes
A200: IM45075681 | B200: 45617 | C200: 45628 | D200: Closed | E200: GUNDAP04 | F200: =IF(ISBLANK(C200), NETWORKDAYS(B200,TODAY()), NETWORKDAYS(B200,C200)) -> 8 | G200: PASSPORT | H200: Patient Insights | TF_FAL_PAC_LOAD failure 11/21 | I200: Data Issue | J200: IICS | K200: DINALIS, KONSTANTINOS | L200: Project Team | M200: =VLOOKUP(Incidents[[#This Row],[Ticket ID]],[1]Incidents!$A$2:$D$792,4,FALSE) -> 2 - High | N200: =VLOOKUP(Incidents[[#This Row],[Priority]],'SLA Config'!$B$3:$C$6,2,FALSE) -> 5 | O200: =IF(Incidents[[#This Row],[Age (days)]]>Incidents[[#This Row],[SLA Threshold]],"NO","Yes") -> NO
A201: IM45243138 | B201: 45679 | C201: 45689 | D201: Closed | E201: ANANDA40 | F201: =IF(ISBLANK(C201), NETWORKDAYS(B201,TODAY()), NETWORKDAYS(B201,C201)) -> 8 | G201: OTHER | H201: Update data for OSOT Dashboard - Route to GBL-C4 MARM PATIENT INSIGHTS SUPPORT | I201: Data Issue | K201: ANAND, ASHISH | L201: Support | M201: =VLOOKUP(Incidents[[#This Row],[Ticket ID]],[1]Incidents!$A$2:$D$792,4,FALSE) -> 2 - High | N201: =VLOOKUP(Incidents[[#This Row],[Priority]],'SLA Config'!$B$3:$C$6,2,FALSE) -> 5 | O201: =IF(Incidents[[#This Row],[Age (days)]]>Incidents[[#This Row],[SLA Threshold]],"NO","Yes") -> NO
A202: IM42560753 | B202: 44900 | C202: 44908 | D202: Closed | E202: SIRIVV02 | F202: =IF(ISBLANK(C202), NETWORKDAYS(B202,TODAY()), NETWORKDAYS(B202,C202)) -> 7 | G202: PASSPORT | H202: Last refresh date in amba dashboard must be 11/25 but it is showing 11/18 | I202: Data Issue | J202: Tableau | K202: DIXIT, RISHI | L202: Business | M202: =VLOOKUP(Incidents[[#This Row],[Ticket ID]],[1]Incidents!$A$2:$D$792,4,FALSE) -> 4 - Low | N202: =VLOOKUP(Incidents[[#This Row],[Priority]],'SLA Config'!$B$3:$C$6,2,FALSE) -> 25 | O202: =IF(Incidents[[#This Row],[Age (days)]]>Incidents[[#This Row],[SLA Threshold]],"NO","Yes") -> Yes
A203: IM42945815 | B203: 45001 | C203: 45011 | D203: Closed | E203: DINALK01 | F203: =IF(ISBLANK(C203), NETWORKDAYS(B203,TODAY()), NETWORKDAYS(B203,C203)) -> 7 | G203: CHAMP | H203: CHAMP - Update/Refresh question | I203: Data Issue | J203: Tableau | K203: DESAI, RAJ | L203: Business | M203: =VLOOKUP(Incidents[[#This Row],[Ticket ID]],[1]Incidents!$A$2:$D$792,4,FALSE) -> 3 - Medium | N203: =VLOOKUP(Incidents[[#This Row],[Priority]],'SLA Config'!$B$3:$C$6,2,FALSE) -> 15 | O203: =IF(Incidents[[#This Row],[Age (days)]]>Incidents[[#This Row],[SLA Threshold]],"NO","Yes") -> Yes
A204: IM42963870 | B204: 45006 | C204: 45014 | D204: Closed | E204: DINALK01 | F204: =IF(ISBLANK(C204), NETWORKDAYS(B204,TODAY()), NETWORKDAYS(B204,C204)) -> 7 | G204: CHAMP | H204: CHAMP | Unmapped SPIF codes | I204: Data Issue | J204: Tableau | K204: DESAI, RAJ | L204: Business | M204: =VLOOKUP(Incidents[[#This Row],[Ticket ID]],[1]Incidents!$A$2:$D$792,4,FALSE) -> 4 - Low | N204: =VLOOKUP(Incidents[[#This Row],[Priority]],'SLA Config'!$B$3:$C$6,2,FALSE) -> 25 | O204: =IF(Incidents[[#This Row],[Age (days)]]>Incidents[[#This Row],[SLA Threshold]],"NO","Yes") -> Yes
A205: IM43493652 | B205: 45155 | C205: 45164 | D205: Closed | E205: GANJIR04 | F205: =IF(ISBLANK(C205), NETWORKDAYS(B205,TODAY()), NETWORKDAYS(B205,C205)) -> 7 | G205: PASSPORT | H205: Data Quality | Only Vyndaqel and Xeljanz brands available | I205: Data Issue | J205: Tableau | K205: DINALIS, KONSTANTINOS | L205: Support | M205: =VLOOKUP(Incidents[[#This Row],[Ticket ID]],[1]Incidents!$A$2:$D$792,4,FALSE) -> 4 - Low | N205: =VLOOKUP(Incidents[[#This Row],[Priority]],'SLA Config'!$B$3:$C$6,2,FALSE) -> 25 | O205: =IF(Incidents[[#This Row],[Age (days)]]>Incidents[[#This Row],[SLA Threshold]],"NO","Yes") -> Yes
A206: IM44059667 | B206: 45313 | C206: 45321 | D206: Closed | E206: ANANDA40 | F206: =IF(ISBLANK(C206), NETWORKDAYS(B206,TODAY()), NETWORKDAYS(B206,C206)) -> 7 | G206: PASSPORT | H206: The Ibrance patient experience report is shown as last updated at 12-Oct-2023 and the most recent quarter is Q2’23. | I206: Data Issue | J206: Tableau | K206: DING, MING | L206: Business | M206: =VLOOKUP(Incidents[[#This Row],[Ticket ID]],[1]Incidents!$A$2:$D$792,4,FALSE) -> 3 - Medium | N206: =VLOOKUP(Incidents[[#This Row],[Priority]],'SLA Config'!$B$3:$C$6,2,FALSE) -> 15 | O206: =IF(Incidents[[#This Row],[Age (days)]]>Incidents[[#This Row],[SLA Threshold]],"NO","Yes") -> Yes
A207: IM44072283 | B207: 45316 | C207: 45326 | D207: Closed | E207: DINALK01 | F207: =IF(ISBLANK(C207), NETWORKDAYS(B207,TODAY()), NETWORKDAYS(B207,C207)) -> 7 | G207: CHAMP | H207: Patient Insights - Data Issue - Champ- (TF_CHAMP_SPIF_KPI_master) | I207: Data Issue | J207: IICS | K207: AKONDI, PRAVEEN | L207: Digital | M207: =VLOOKUP(Incidents[[#This Row],[Ticket ID]],[1]Incidents!$A$2:$D$792,4,FALSE) -> 3 - Medium | N207: =VLOOKUP(Incidents[[#This Row],[Priority]],'SLA Config'!$B$3:$C$6,2,FALSE) -> 15 | O207: =IF(Incidents[[#This Row],[Age (days)]]>Incidents[[#This Row],[SLA Threshold]],"NO","Yes") -> Yes
A208: IM44099506 | B208: 45324 | C208: 45334 | D208: Closed | E208: ANANDA40 | F208: =IF(ISBLANK(C208), NETWORKDAYS(B208,TODAY()), NETWORKDAYS(B208,C208)) -> 7 | G208: PASSPORT | H208: Patient Insights | Texas Account Mapping | I208: Data Issue | J208: Tableau | K208: ANAND, ASHISH | L208: Support | M208: =VLOOKUP(Incidents[[#This Row],[Ticket ID]],[1]Incidents!$A$2:$D$792,4,FALSE) -> 4 - Low | N208: =VLOOKUP(Incidents[[#This Row],[Priority]],'SLA Config'!$B$3:$C$6,2,FALSE) -> 25 | O208: =IF(Incidents[[#This Row],[Age (days)]]>Incidents[[#This Row],[SLA Threshold]],"NO","Yes") -> Yes
A209: IM44354312 | B209: 45400 | C209: 45410 | D209: Closed | E209: BABUS32 | F209: =IF(ISBLANK(C209), NETWORKDAYS(B209,TODAY()), NETWORKDAYS(B209,C209)) -> 7 | G209: PASSPORT | H209: Patient Insights | Patient Experience report is empty | I209: Data Issue | J209: Tableau | K209: GEORGE, AJOY | L209: Project Team | M209: =VLOOKUP(Incidents[[#This Row],[Ticket ID]],[1]Incidents!$A$2:$D$792,4,FALSE) -> 2 - High | N209: =VLOOKUP(Incidents[[#This Row],[Priority]],'SLA Config'!$B$3:$C$6,2,FALSE) -> 5 | O209: =IF(Incidents[[#This Row],[Age (days)]]>Incidents[[#This Row],[SLA Threshold]],"NO","Yes") -> NO
A210: IM44379645 | B210: 45407 | C210: 45416 | D210: Closed | E210: MALLIA04 | F210: =IF(ISBLANK(C210), NETWORKDAYS(B210,TODAY()), NETWORKDAYS(B210,C210)) -> 7 | G210: PASSPORT | H210: Passport dashboard - Internal | I210: Data Issue | J210: Tableau | K210: DESAI, RAJ | L210: Business | M210: =VLOOKUP(Incidents[[#This Row],[Ticket ID]],[1]Incidents!$A$2:$D$792,4,FALSE) -> 3 - Medium | N210: =VLOOKUP(Incidents[[#This Row],[Priority]],'SLA Config'!$B$3:$C$6,2,FALSE) -> 15 | O210: =IF(Incidents[[#This Row],[Age (days)]]>Incidents[[#This Row],[SLA Threshold]],"NO","Yes") -> Yes
A211: IM44947189 | B211: 45579 | C211: 45586 | D211: Closed | E211: ANANDA40 | F211: =IF(ISBLANK(C211), NETWORKDAYS(B211,TODAY()), NETWORKDAYS(B211,C211)) -> 6 | G211: PASSPORT | H211: Patient Insights - Data Issue | I211: Data Issue | J211: Tableau | K211: MUTHURAMALINGAM, VIMALA GOKULAM | L211: Digital | M211: =VLOOKUP(Incidents[[#This Row],[Ticket ID]],[1]Incidents!$A$2:$D$792,4,FALSE) -> 2 - High | N211: =VLOOKUP(Incidents[[#This Row],[Priority]],'SLA Config'!$B$3:$C$6,2,FALSE) -> 5 | O211: =IF(Incidents[[#This Row],[Age (days)]]>Incidents[[#This Row],[SLA Threshold]],"NO","Yes") -> NO
A212: IM45075592 | B212: 45617 | C212: 45626 | D212: Closed | E212: GUNDAP04 | F212: =IF(ISBLANK(C212), NETWORKDAYS(B212,TODAY()), NETWORKDAYS(B212,C212)) -> 7 | G212: PASSPORT | H212: Patient Insights | DERM master load failed 11/20 | I212: Data Issue | J212: IICS | K212: DINALIS, KONSTANTINOS | L212: Project Team | M212: =VLOOKUP(Incidents[[#This Row],[Ticket ID]],[1]Incidents!$A$2:$D$792,4,FALSE) -> 2 - High | N212: =VLOOKUP(Incidents[[#This Row],[Priority]],'SLA Config'!$B$3:$C$6,2,FALSE) -> 5 | O212: =IF(Incidents[[#This Row],[Age (days)]]>Incidents[[#This Row],[SLA Threshold]],"NO","Yes") -> NO
A213: IM42664133 | B213: 44929 | C213: 44936 | D213: Closed | E213: SIRIVV02 | F213: =IF(ISBLANK(C213), NETWORKDAYS(B213,TODAY()), NETWORKDAYS(B213,C213)) -> 6 | G213: PASSPORT | H213: Patient Insights - Application Issue | I213: Data Issue | J213: Web App | K213: DESAI, RAJ | L213: Business | M213: =VLOOKUP(Incidents[[#This Row],[Ticket ID]],[1]Incidents!$A$2:$D$792,4,FALSE) -> 4 - Low | N213: =VLOOKUP(Incidents[[#This Row],[Priority]],'SLA Config'!$B$3:$C$6,2,FALSE) -> 25 | O213: =IF(Incidents[[#This Row],[Age (days)]]>Incidents[[#This Row],[SLA Threshold]],"NO","Yes") -> Yes
... A221: IM44820207 | B221: 45539 | C221: 45546 | D221: Closed | E221: BABUS32 | F221: =IF(ISBLANK(C221), NETWORKDAYS(B221,TODAY()), NETWORKDAYS(B221,C221)) -> 6 | G221: CHAMP | H221: Patient Insights - Patient Point Data Issue | I221: Data Issue | J221: Web App | K221: AKONDI, PRAVEEN | L221: Digital | M221: =VLOOKUP(Incidents[[#This Row],[Ticket ID]],[1]Incidents!$A$2:$D$792,4,FALSE) -> 4 - Low | N221: =VLOOKUP(Incidents[[#This Row],[Priority]],'SLA Config'!$B$3:$C$6,2,FALSE) -> 25 | O221: =IF(Incidents[[#This Row],[Age (days)]]>Incidents[[#This Row],[SLA Threshold]],"NO","Yes") -> Yes
A222: IM45232194 | B222: 45674 | C222: 45682 | D222: Closed | E222: GUNDAP04 | F222: =IF(ISBLANK(C222), NETWORKDAYS(B222,TODAY()), NETWORKDAYS(B222,C222)) -> 6 | G222: PASSPORT | H222: Patient Insights | BRIDGE | HUB interface failure on 01/15/2025 | I222: Data Issue | K222: GUNDANNA, PUNYA | L222: Support | M222: =VLOOKUP(Incidents[[#This Row],[Ticket ID]],[1]Incidents!$A$2:$D$792,4,FALSE) -> 4 - Low | N222: =VLOOKUP(Incidents[[#This Row],[Priority]],'SLA Config'!$B$3:$C$6,2,FALSE) -> 25 | O222: =IF(Incidents[[#This Row],[Age (days)]]>Incidents[[#This Row],[SLA Threshold]],"NO","Yes") -> Yes
A223: IM45323470 | B223: 45706 | C223: 45796 | D223: Closed | E223: MALLIA04 | F223: =IF(ISBLANK(C223), NETWORKDAYS(B223,TODAY()), NETWORKDAYS(B223,C223)) -> 65 | G223: PASSPORT | H223: Patient Insights - Data Issue - Velsipity - Baseline Assessment Value Issue | I223: Data Issue | K223: DING, MING | L223: Business | M223: =VLOOKUP(Incidents[[#This Row],[Ticket ID]],[1]Incidents!$A$2:$D$792,4,FALSE) -> 2 - High | N223: =VLOOKUP(Incidents[[#This Row],[Priority]],'SLA Config'!$B$3:$C$6,2,FALSE) -> 5 | O223: =IF(Incidents[[#This Row],[Age (days)]]>Incidents[[#This Row],[SLA Threshold]],"NO","Yes") -> NO
A224: IM45249196 | B224: 45680 | C224: 45727 | D224: Closed | E224: CHANDU06 | F224: =IF(ISBLANK(C224), NETWORKDAYS(B224,TODAY()), NETWORKDAYS(B224,C224)) -> 34 | G224: CHAMP | H224: Update the Primary Care FAL and PAC dashboard Route to GBL-C4 MARM PATIENT INSIGHTS SUPPORT | I224: Data Issue | J224: Tableau | K224: SAMIAYYAN, SHANMUGAM | L224: Digital | M224: =VLOOKUP(Incidents[[#This Row],[Ticket ID]],[1]Incidents!$A$2:$D$792,4,FALSE) -> 4 - Low | N224: =VLOOKUP(Incidents[[#This Row],[Priority]],'SLA Config'!$B$3:$C$6,2,FALSE) -> 25 | O224: =IF(Incidents[[#This Row],[Age (days)]]>Incidents[[#This Row],[SLA Threshold]],"NO","Yes") -> NO
A225: IM43347198 | B225: 45113 | C225: 45119 | D225: Closed | F225: =IF(ISBLANK(C225), NETWORKDAYS(B225,TODAY()), NETWORKDAYS(B225,C225)) -> 5 | G225: CHAMP | H225: CHAMP | SPIF unmapped even if mapping is setup on Patient Point | I225: Data Issue | J225: Tableau | K225: TROUGHT, ALLISON | L225: Business | M225: =VLOOKUP(Incidents[[#This Row],[Ticket ID]],[1]Incidents!$A$2:$D$792,4,FALSE) -> 3 - Medium | N225: =VLOOKUP(Incidents[[#This Row],[Priority]],'SLA Config'!$B$3:$C$6,2,FALSE) -> 15 | O225: =IF(Incidents[[#This Row],[Age (days)]]>Incidents[[#This Row],[SLA Threshold]],"NO","Yes") -> Yes
A226: IM43410763 | B226: 45132 | C226: 45138 | D226: Closed | E226: BABUS32 | F226: =IF(ISBLANK(C226), NETWORKDAYS(B226,TODAY()), NETWORKDAYS(B226,C226)) -> 5 | G226: CHAMP | H226: Patient Point | Duplication error while updating contract 4832 | I226: Data Issue | J226: Web App | K226: TROUGHT, ALLISON | L226: Business | M226: =VLOOKUP(Incidents[[#This Row],[Ticket ID]],[1]Incidents!$A$2:$D$792,4,FALSE) -> 3 - Medium | N226: =VLOOKUP(Incidents[[#This Row],[Priority]],'SLA Config'!$B$3:$C$6,2,FALSE) -> 15 | O226: =IF(Incidents[[#This Row],[Age (days)]]>Incidents[[#This Row],[SLA Threshold]],"NO","Yes") -> Yes
A227: IM43603660 | B227: 45183 | C227: 45189 | D227: Closed | E227: DINALK01 | F227: =IF(ISBLANK(C227), NETWORKDAYS(B227,TODAY()), NETWORKDAYS(B227,C227)) -> 5 | G227: CHAMP | H227: Patient Insights - CHAMP Elixir-Inlyta SPIF missing incorrectly | I227: Data Issue | J227: Tableau | K227: TROUGHT, ALLISON | L227: Business | M227: =VLOOKUP(Incidents[[#This Row],[Ticket ID]],[1]Incidents!$A$2:$D$792,4,FALSE) -> 3 - Medium | N227: =VLOOKUP(Incidents[[#This Row],[Priority]],'SLA Config'!$B$3:$C$6,2,FALSE) -> 15 | O227: =IF(Incidents[[#This Row],[Age (days)]]>Incidents[[#This Row],[SLA Threshold]],"NO","Yes") -> Yes
A228: IM43926374 | B228: 45273 | C228: 45279 | D228: Closed | E228: DINALK01 | F228: =IF(ISBLANK(C228), NETWORKDAYS(B228,TODAY()), NETWORKDAYS(B228,C228)) -> 5 | G228: CHAMP | H228: Patient Point | Budget needs to be reverted back | I228: Data Issue | J228: Snowflake | K228: TROUGHT, ALLISON | L228: Business | M228: =VLOOKUP(Incidents[[#This Row],[Ticket ID]],[1]Incidents!$A$2:$D$792,4,FALSE) -> 2 - High | N228: =VLOOKUP(Incidents[[#This Row],[Priority]],'SLA Config'!$B$3:$C$6,2,FALSE) -> 5 | O228: =IF(Incidents[[#This Row],[Age (days)]]>Incidents[[#This Row],[SLA Threshold]],"NO","Yes") -> Yes
A229: IM44112581 | B229: 45328 | C229: 45334 | D229: Closed | E229: ANANDA40 | F229: =IF(ISBLANK(C229), NETWORKDAYS(B229,TODAY()), NETWORKDAYS(B229,C229)) -> 5 | G229: PASSPORT | H229: Patient Insights | Inquiry - CenterWell Q4 Braftovi | I229: Data Issue | J229: Tableau | K229: OSIPOWER, LISA | L229: Business | M229: =VLOOKUP(Incidents[[#This Row],[Ticket ID]],[1]Incidents!$A$2:$D$792,4,FALSE) -> 4 - Low | N229: =VLOOKUP(Incidents[[#This Row],[Priority]],'SLA Config'!$B$3:$C$6,2,FALSE) -> 25 | O229: =IF(Incidents[[#This Row],[Age (days)]]>Incidents[[#This Row],[SLA Threshold]],"NO","Yes") -> Yes
A230: IM44175761 | B230: 45348 | C230: 45354 | D230: Closed | E230: DINALK01 | F230: =IF(ISBLANK(C230), NETWORKDAYS(B230,TODAY()), NETWORKDAYS(B230,C230)) -> 5 | G230: PASSPORT | H230: Patient Insights - Pending patient disappeared Acaria/Q4/Braftovi | I230: Data Issue | J230: Tableau | K230: OSIPOWER, LISA | L230: Business | M230: =VLOOKUP(Incidents[[#This Row],[Ticket ID]],[1]Incidents!$A$2:$D$792,4,FALSE) -> 4 - Low | N230: =VLOOKUP(Incidents[[#This Row],[Priority]],'SLA Config'!$B$3:$C$6,2,FALSE) -> 25 | O230: =IF(Incidents[[#This Row],[Age (days)]]>Incidents[[#This Row],[SLA Threshold]],"NO","Yes") -> Yes
A231: IM44175818 | B231: 45348 | C231: 45353 | D231: Closed | E231: DINALK01 | F231: =IF(ISBLANK(C231), NETWORKDAYS(B231,TODAY()), NETWORKDAYS(B231,C231)) -> 5 | G231: PASSPORT | H231: Patient Insights - Kroger/Q4/Braftovi missing new patient in Efficiency tab | I231: Data Issue | J231: Tableau | K231: OSIPOWER, LISA | L231: Business | M231: =VLOOKUP(Incidents[[#This Row],[Ticket ID]],[1]Incidents!$A$2:$D$792,4,FALSE) -> 4 - Low | N231: =VLOOKUP(Incidents[[#This Row],[Priority]],'SLA Config'!$B$3:$C$6,2,FALSE) -> 25 | O231: =IF(Incidents[[#This Row],[Age (days)]]>Incidents[[#This Row],[SLA Threshold]],"NO","Yes") -> Yes
A232: IM44256640 | B232: 45371 | C232: 45377 | D232: Closed | E232: DINALK01 | F232: =IF(ISBLANK(C232), NETWORKDAYS(B232,TODAY()), NETWORKDAYS(B232,C232)) -> 5 | G232: CHAMP | H232: Patient Insights - CHAMP SPP Validation tab - Velsipity missing | I232: Data Issue | J232: Tableau | K232: TROUGHT, ALLISON | L232: Business | M232: =VLOOKUP(Incidents[[#This Row],[Ticket ID]],[1]Incidents!$A$2:$D$792,4,FALSE) -> 4 - Low | N232: =VLOOKUP(Incidents[[#This Row],[Priority]],'SLA Config'!$B$3:$C$6,2,FALSE) -> 25 | O232: =IF(Incidents[[#This Row],[Age (days)]]>Incidents[[#This Row],[SLA Threshold]],"NO","Yes") -> Yes
A233: IM44420684 | B233: 45418 | C233: 45424 | D233: Closed | E233: ANANDA40 | F233: =IF(ISBLANK(C233), NETWORKDAYS(B233,TODAY()), NETWORKDAYS(B233,C233)) -> 5 | G233: CHAMP | H233: Patient Insights - Application Issue | I233: Data Issue | J233: Tableau | K233: TROUGHT, ALLISON | L233: Business | M233: =VLOOKUP(Incidents[[#This Row],[Ticket ID]],[1]Incidents!$A$2:$D$792,4,FALSE) -> 2 - High | N233: =VLOOKUP(Incidents[[#This Row],[Priority]],'SLA Config'!$B$3:$C$6,2,FALSE) -> 5 | O233: =IF(Incidents[[#This Row],[Age (days)]]>Incidents[[#This Row],[SLA Threshold]],"NO","Yes") -> Yes
A234: IM44508435 | B234: 45446 | C234: 45452 | D234: Closed | E234: MALLIA04 | F234: =IF(ISBLANK(C234), NETWORKDAYS(B234,TODAY()), NETWORKDAYS(B234,C234)) -> 5 | G234: CHAMP | H234: Patient Insights - CHAMP not refreshed as expected | I234: Data Issue | J234: Tableau | K234: TROUGHT, ALLISON | L234: Business | M234: =VLOOKUP(Incidents[[#This Row],[Ticket ID]],[1]Incidents!$A$2:$D$792,4,FALSE) -> 2 - High | N234: =VLOOKUP(Incidents[[#This Row],[Priority]],'SLA Config'!$B$3:$C$6,2,FALSE) -> 5 | O234: =IF(Incidents[[#This Row],[Age (days)]]>Incidents[[#This Row],[SLA Threshold]],"NO","Yes") -> Yes
A235: IM45075647 | B235: 45617 | C235: 45623 | D235: Closed | E235: GUNDAP04 | F235: =IF(ISBLANK(C235), NETWORKDAYS(B235,TODAY()), NETWORKDAYS(B235,C235)) -> 5 | G235: PASSPORT | H235: Patient Insights | TF_FRM_ENGMT_LOAD failure 11/20 | I235: Data Issue | J235: IICS | K235: DINALIS, KONSTANTINOS | L235: Project Team | M235: =VLOOKUP(Incidents[[#This Row],[Ticket ID]],[1]Incidents!$A$2:$D$792,4,FALSE) -> 2 - High | N235: =VLOOKUP(Incidents[[#This Row],[Priority]],'SLA Config'!$B$3:$C$6,2,FALSE) -> 5 | O235: =IF(Incidents[[#This Row],[Age (days)]]>Incidents[[#This Row],[SLA Threshold]],"NO","Yes") -> Yes
A236: IM45107059 | B236: 45628 | C236: 45633 | D236: Closed | E236: CHANDU06 | F236: =IF(ISBLANK(C236), NETWORKDAYS(B236,TODAY()), NETWORKDAYS(B236,C236)) -> 5 | G236: CHAMP | H236: Patient Insights - System Performance or Failure | I236: Data Issue | J236: Performance | K236: TROUGHT, ALLISON | L236: Business | M236: =VLOOKUP(Incidents[[#This Row],[Ticket ID]],[1]Incidents!$A$2:$D$792,4,FALSE) -> 2 - High | N236: =VLOOKUP(Incidents[[#This Row],[Priority]],'SLA Config'!$B$3:$C$6,2,FALSE) -> 5 | O236: =IF(Incidents[[#This Row],[Age (days)]]>Incidents[[#This Row],[SLA Threshold]],"NO","Yes") -> Yes
A237: IM45198941 | B237: 45664 | C237: 45670 | D237: Closed | E237: ANANDA40 | F237: =IF(ISBLANK(C237), NETWORKDAYS(B237,TODAY()), NETWORKDAYS(B237,C237)) -> 5 | G237: PASSPORT | H237: Patient Insights | PatientInsights_Master_Load Failure | I237: Data Issue | J237: IICS | K237: ANAND, ASHISH | L237: Support | M237: =VLOOKUP(Incidents[[#This Row],[Ticket ID]],[1]Incidents!$A$2:$D$792,4,FALSE) -> 3 - Medium | N237: =VLOOKUP(Incidents[[#This Row],[Priority]],'SLA Config'!$B$3:$C$6,2,FALSE) -> 15 | O237: =IF(Incidents[[#This Row],[Age (days)]]>Incidents[[#This Row],[SLA Threshold]],"NO","Yes") -> Yes
... A241: IM44239566 | B241: 45366 | C241: 45371 | D241: Closed | E241: DINALK01 | F241: =IF(ISBLANK(C241), NETWORKDAYS(B241,TODAY()), NETWORKDAYS(B241,C241)) -> 4 | G241: CHAMP | H241: Patient Insights -CHAMP Lumicera-Xeljanz unmapped files | I241: Data Issue | J241: Tableau | K241: TROUGHT, ALLISON | L241: Business | M241: =VLOOKUP(Incidents[[#This Row],[Ticket ID]],[1]Incidents!$A$2:$D$792,4,FALSE) -> 2 - High | N241: =VLOOKUP(Incidents[[#This Row],[Priority]],'SLA Config'!$B$3:$C$6,2,FALSE) -> 5 | O241: =IF(Incidents[[#This Row],[Age (days)]]>Incidents[[#This Row],[SLA Threshold]],"NO","Yes") -> Yes
A242: IM45350064 | B242: 45714 | C242: 45726 | D242: Closed | E242: ANANDA40 | F242: =IF(ISBLANK(C242), NETWORKDAYS(B242,TODAY()), NETWORKDAYS(B242,C242)) -> 9 | G242: PASSPORT | H242: Passport Dispensed volume blank | I242: Data Issue | K242: DESAI, RAJ | L242: Business | M242: =VLOOKUP(Incidents[[#This Row],[Ticket ID]],[1]Incidents!$A$2:$D$792,4,FALSE) -> 2 - High | N242: =VLOOKUP(Incidents[[#This Row],[Priority]],'SLA Config'!$B$3:$C$6,2,FALSE) -> 5 | O242: =IF(Incidents[[#This Row],[Age (days)]]>Incidents[[#This Row],[SLA Threshold]],"NO","Yes") -> NO
A243: IM45285776 | B243: 45693 | C243: 45724 | D243: Closed | E243: MALLIA04 | F243: =IF(ISBLANK(C243), NETWORKDAYS(B243,TODAY()), NETWORKDAYS(B243,C243)) -> 23 | G243: CHAMP | H243: Patient Insights - Data Issue | I243: Data Issue | K243: TROUGHT, ALLISON | L243: Business | M243: =VLOOKUP(Incidents[[#This Row],[Ticket ID]],[1]Incidents!$A$2:$D$792,4,FALSE) -> 2 - High | N243: =VLOOKUP(Incidents[[#This Row],[Priority]],'SLA Config'!$B$3:$C$6,2,FALSE) -> 5 | O243: =IF(Incidents[[#This Row],[Age (days)]]>Incidents[[#This Row],[SLA Threshold]],"NO","Yes") -> NO
A244: IM45317517 | B244: 45705 | C244: 45719 | D244: Closed | E244: MALLIA04 | F244: =IF(ISBLANK(C244), NETWORKDAYS(B244,TODAY()), NETWORKDAYS(B244,C244)) -> 11 | G244: CHAMP | H244: Patient Insights FRM Users alignment with Troy's File | I244: Data Issue | K244: NISHAD, AMARCHAND SATYANARAYAN | M244: =VLOOKUP(Incidents[[#This Row],[Ticket ID]],[1]Incidents!$A$2:$D$792,4,FALSE) -> 4 - Low | N244: =VLOOKUP(Incidents[[#This Row],[Priority]],'SLA Config'!$B$3:$C$6,2,FALSE) -> 25 | O244: =IF(Incidents[[#This Row],[Age (days)]]>Incidents[[#This Row],[SLA Threshold]],"NO","Yes") -> Yes
A245: IM45291325 | B245: 45695 | C245: 45717 | D245: Closed | E245: ANANDA40 | F245: =IF(ISBLANK(C245), NETWORKDAYS(B245,TODAY()), NETWORKDAYS(B245,C245)) -> 16 | G245: PASSPORT | H245: Refresh Tables from PROD to DEV & UAT | I245: Data Issue | K245: PATRO, P SAURAV KUMAR | L245: Digital | M245: =VLOOKUP(Incidents[[#This Row],[Ticket ID]],[1]Incidents!$A$2:$D$792,4,FALSE) -> 4 - Low | N245: =VLOOKUP(Incidents[[#This Row],[Priority]],'SLA Config'!$B$3:$C$6,2,FALSE) -> 25 | O245: =IF(Incidents[[#This Row],[Age (days)]]>Incidents[[#This Row],[SLA Threshold]],"NO","Yes") -> Yes
A246: IM45310930 | B246: 45701 | C246: 45717 | D246: Closed | E246: GUNDAP04 | F246: =IF(ISBLANK(C246), NETWORKDAYS(B246,TODAY()), NETWORKDAYS(B246,C246)) -> 12 | G246: PASSPORT | H246: Patient Insights FRM USER_XREF_ROLE Mapping Fix | I246: Data Issue | K246: KARDI, PANDE PUTU ADYSTI | L246: Digital | M246: =VLOOKUP(Incidents[[#This Row],[Ticket ID]],[1]Incidents!$A$2:$D$792,4,FALSE) -> 4 - Low | N246: =VLOOKUP(Incidents[[#This Row],[Priority]],'SLA Config'!$B$3:$C$6,2,FALSE) -> 25 | O246: =IF(Incidents[[#This Row],[Age (days)]]>Incidents[[#This Row],[SLA Threshold]],"NO","Yes") -> Yes
A247: IM41736552 | B247: 44700 | C247: 44808 | D247: Closed | E247: MALLIA04 | F247: =IF(ISBLANK(C247), NETWORKDAYS(B247,TODAY()), NETWORKDAYS(B247,C247)) -> 77 | G247: CHAMP | H247: To track the list of SOP's for Patient Insight Application | I247: Documentation | J247: SOP | K247: MALLIKARJUN INGALALLI, ANUPAMA | L247: Support | M247: =VLOOKUP(Incidents[[#This Row],[Ticket ID]],[1]Incidents!$A$2:$D$792,4,FALSE) -> 4 - Low | N247: =VLOOKUP(Incidents[[#This Row],[Priority]],'SLA Config'!$B$3:$C$6,2,FALSE) -> 25 | O247: =IF(Incidents[[#This Row],[Age (days)]]>Incidents[[#This Row],[SLA Threshold]],"NO","Yes") -> NO
A248: IM44982114 | B248: 45588 | C248: 45634 | D248: Closed | E248: GUNDAP04 | F248: =IF(ISBLANK(C248), NETWORKDAYS(B248,TODAY()), NETWORKDAYS(B248,C248)) -> 33 | G248: PASSPORT | H248: Update Patient Insights FAL PAC geography alignments | I248: Enhancement | J248: Data Update | K248: KARDI, PANDE PUTU ADYSTI | L248: Digital | M248: =VLOOKUP(Incidents[[#This Row],[Ticket ID]],[1]Incidents!$A$2:$D$792,4,FALSE) -> 4 - Low | N248: =VLOOKUP(Incidents[[#This Row],[Priority]],'SLA Config'!$B$3:$C$6,2,FALSE) -> 25 | O248: =IF(Incidents[[#This Row],[Age (days)]]>Incidents[[#This Row],[SLA Threshold]],"NO","Yes") -> NO
A249: IM45263137 | B249: 45686 | C249: 45693 | D249: Closed | E249: ANANDA40 | F249: =IF(ISBLANK(C249), NETWORKDAYS(B249,TODAY()), NETWORKDAYS(B249,C249)) -> 6 | G249: PASSPORT | H249: Patient Insight | TF_CHAMP_SPIF_KPI_MASTER | 28th January 2025 | I249: Enhancement | J249: IICS | K249: ANAND, ASHISH | L249: Support | M249: =VLOOKUP(Incidents[[#This Row],[Ticket ID]],[1]Incidents!$A$2:$D$792,4,FALSE) -> 2 - High | N249: =VLOOKUP(Incidents[[#This Row],[Priority]],'SLA Config'!$B$3:$C$6,2,FALSE) -> 5 | O249: =IF(Incidents[[#This Row],[Age (days)]]>Incidents[[#This Row],[SLA Threshold]],"NO","Yes") -> NO
A250: IM45191186 | B250: 45660 | C250: 45747 | D250: Closed | E250: ANANDA40 | F250: =IF(ISBLANK(C250), NETWORKDAYS(B250,TODAY()), NETWORKDAYS(B250,C250)) -> 62 | G250: PASSPORT | H250: Data Point for PA CMM Status in KPI Engagement Report | I250: Environment | K250: GOLLER, MARK | L250: Business | M250: =VLOOKUP(Incidents[[#This Row],[Ticket ID]],[1]Incidents!$A$2:$D$792,4,FALSE) -> 3 - Medium | N250: =VLOOKUP(Incidents[[#This Row],[Priority]],'SLA Config'!$B$3:$C$6,2,FALSE) -> 15 | O250: =IF(Incidents[[#This Row],[Age (days)]]>Incidents[[#This Row],[SLA Threshold]],"NO","Yes") -> NO
A251: IM43636894 | B251: 45194 | C251: 45256 | D251: Closed | E251: BABUS32 | F251: =IF(ISBLANK(C251), NETWORKDAYS(B251,TODAY()), NETWORKDAYS(B251,C251)) -> 45 | G251: PASSPORT | H251: Patient Insights | GitHub Dependabot alerts | I251: Environment | J251: Dependabot | K251: SAMIAYYAN, SHANMUGAM | L251: Digital | M251: =VLOOKUP(Incidents[[#This Row],[Ticket ID]],[1]Incidents!$A$2:$D$792,4,FALSE) -> 4 - Low | N251: =VLOOKUP(Incidents[[#This Row],[Priority]],'SLA Config'!$B$3:$C$6,2,FALSE) -> 25 | O251: =IF(Incidents[[#This Row],[Age (days)]]>Incidents[[#This Row],[SLA Threshold]],"NO","Yes") -> NO
A252: IM41852377 | B252: 44728 | C252: 44754 | D252: Closed | E252: MALLIA04 | F252: =IF(ISBLANK(C252), NETWORKDAYS(B252,TODAY()), NETWORKDAYS(B252,C252)) -> 19 | G252: PASSPORT | H252: Automated set up required for DEV cdw tables refresh | I252: Environment | J252: Data Refresh | K252: MALLIKARJUN INGALALLI, ANUPAMA | L252: Project Team | M252: =VLOOKUP(Incidents[[#This Row],[Ticket ID]],[1]Incidents!$A$2:$D$792,4,FALSE) -> 4 - Low | N252: =VLOOKUP(Incidents[[#This Row],[Priority]],'SLA Config'!$B$3:$C$6,2,FALSE) -> 25 | O252: =IF(Incidents[[#This Row],[Age (days)]]>Incidents[[#This Row],[SLA Threshold]],"NO","Yes") -> Yes
A253: IM45233229 | B253: 45674 | C253: 45698 | D253: Closed | E253: ANANDA40 | F253: =IF(ISBLANK(C253), NETWORKDAYS(B253,TODAY()), NETWORKDAYS(B253,C253)) -> 17 | G253: PASSPORT | H253: PI Specialty Care FRM Dashboard I&I Zip2Terr issue | I253: Environment | J253: Tableau | K253: WANG, ERIC | L253: Business | M253: =VLOOKUP(Incidents[[#This Row],[Ticket ID]],[1]Incidents!$A$2:$D$792,4,FALSE) -> 2 - High | N253: =VLOOKUP(Incidents[[#This Row],[Priority]],'SLA Config'!$B$3:$C$6,2,FALSE) -> 5 | O253: =IF(Incidents[[#This Row],[Age (days)]]>Incidents[[#This Row],[SLA Threshold]],"NO","Yes") -> NO
A254: IM45221191 | B254: 45671 | C254: 45692 | D254: Closed | E254: CHANDU06 | F254: =IF(ISBLANK(C254), NETWORKDAYS(B254,TODAY()), NETWORKDAYS(B254,C254)) -> 16 | G254: PASSPORT | H254: OPSA Field Access Analytics Dashboard | I254: Environment | J254: Tableau | K254: PAL, SARIKA | M254: =VLOOKUP(Incidents[[#This Row],[Ticket ID]],[1]Incidents!$A$2:$D$792,4,FALSE) -> 4 - Low | N254: =VLOOKUP(Incidents[[#This Row],[Priority]],'SLA Config'!$B$3:$C$6,2,FALSE) -> 25 | O254: =IF(Incidents[[#This Row],[Age (days)]]>Incidents[[#This Row],[SLA Threshold]],"NO","Yes") -> Yes
A255: IM45210734 | B255: 45667 | C255: 45686 | D255: Closed | E255: ANANDA40 | F255: =IF(ISBLANK(C255), NETWORKDAYS(B255,TODAY()), NETWORKDAYS(B255,C255)) -> 14 | G255: OTHER | H255: UAT and Production Files Upload | I255: Environment | K255: JAYAPRAKASH, PRADEESH D | M255: =VLOOKUP(Incidents[[#This Row],[Ticket ID]],[1]Incidents!$A$2:$D$792,4,FALSE) -> 2 - High | N255: =VLOOKUP(Incidents[[#This Row],[Priority]],'SLA Config'!$B$3:$C$6,2,FALSE) -> 5 | O255: =IF(Incidents[[#This Row],[Age (days)]]>Incidents[[#This Row],[SLA Threshold]],"NO","Yes") -> NO
A256: IM44707919 | B256: 45503 | C256: 45517 | D256: Closed | E256: ANANDA40 | F256: =IF(ISBLANK(C256), NETWORKDAYS(B256,TODAY()), NETWORKDAYS(B256,C256)) -> 11 | G256: PASSPORT | H256: TABLEAU | FW: PRESCRIBER_NEW_WRITER_VW (PNTINSIGHT_RPT) Extract Refresh Failed | I256: Environment | J256: Tableau | K256: MORE, SHAILESH | L256: Digital | M256: =VLOOKUP(Incidents[[#This Row],[Ticket ID]],[1]Incidents!$A$2:$D$792,4,FALSE) -> 4 - Low | N256: =VLOOKUP(Incidents[[#This Row],[Priority]],'SLA Config'!$B$3:$C$6,2,FALSE) -> 25 | O256: =IF(Incidents[[#This Row],[Age (days)]]>Incidents[[#This Row],[SLA Threshold]],"NO","Yes") -> Yes
A257: IM45175397 | B257: 45653 | C257: 45669 | D257: Closed | E257: ANANDA40 | F257: =IF(ISBLANK(C257), NETWORKDAYS(B257,TODAY()), NETWORKDAYS(B257,C257)) -> 11 | G257: PASSPORT | H257: Patient Insights | GenWizard Model Upgrade Stage Testing | I257: Environment | K257: ANAND, ASHISH | L257: Support | M257: =VLOOKUP(Incidents[[#This Row],[Ticket ID]],[1]Incidents!$A$2:$D$792,4,FALSE) -> 4 - Low | N257: =VLOOKUP(Incidents[[#This Row],[Priority]],'SLA Config'!$B$3:$C$6,2,FALSE) -> 25 | O257: =IF(Incidents[[#This Row],[Age (days)]]>Incidents[[#This Row],[SLA Threshold]],"NO","Yes") -> Yes
A258: IM44690236 | B258: 45498 | C258: 45511 | D258: Closed | E258: ANANDA40 | F258: =IF(ISBLANK(C258), NETWORKDAYS(B258,TODAY()), NETWORKDAYS(B258,C258)) -> 10 | G258: PASSPORT | H258: Patient Insights | Scorecard Dashboard Extract Refresh Failed | I258: Environment | J258: Tableau | K258: DINALIS, KONSTANTINOS | L258: Support | M258: =VLOOKUP(Incidents[[#This Row],[Ticket ID]],[1]Incidents!$A$2:$D$792,4,FALSE) -> 3 - Medium | N258: =VLOOKUP(Incidents[[#This Row],[Priority]],'SLA Config'!$B$3:$C$6,2,FALSE) -> 15 | O258: =IF(Incidents[[#This Row],[Age (days)]]>Incidents[[#This Row],[SLA Threshold]],"NO","Yes") -> Yes
A259: IM45042035 | B259: 45607 | C259: 45619 | D259: Closed | E259: CHANDU06 | F259: =IF(ISBLANK(C259), NETWORKDAYS(B259,TODAY()), NETWORKDAYS(B259,C259)) -> 10 | G259: TABLEAU | H259: TABLEAU | FW: Data Quality Management Dashboard Extract Refresh Failed | I259: Environment | J259: IICS | K259: MORE, SHAILESH | L259: Digital | M259: =VLOOKUP(Incidents[[#This Row],[Ticket ID]],[1]Incidents!$A$2:$D$792,4,FALSE) -> 4 - Low | N259: =VLOOKUP(Incidents[[#This Row],[Priority]],'SLA Config'!$B$3:$C$6,2,FALSE) -> 25 | O259: =IF(Incidents[[#This Row],[Age (days)]]>Incidents[[#This Row],[SLA Threshold]],"NO","Yes") -> Yes
...

Sheet Requests
A1: Ticket ID | B1: Opened On | C1: Closed On | D1: Status | E1: Assignee | F1: Age (days) | G1: Application Affected | H1: Brief Description | I1: Category | J1: Subcategory | K1: Reporter | L1: Requested By | M1: Priority | N1: SLA Threshold | O1: SLAs Met?
A2: RF3622712 | B2: 44648 | C2: 44662 | D2: Closed | E2: MALLIA04 | F2: =IF(ISBLANK(C2), NETWORKDAYS(B2,TODAY()), NETWORKDAYS(B2,C2)) -> 11 | G2: CHAMP | H2: GMFT reconfiguration required in DEV S3 | I2: Enhancement | J2: Batch | K2: SHAJI, GENUINE | L2: Digital | M2: =VLOOKUP(Requests[[#This Row],[Ticket ID]],[2]Requests!$A$2:$D$649,4,FALSE) -> 4 - Low | N2: =VLOOKUP(Requests[[#This Row],[Priority]],'SLA Config'!$B$3:$C$6,2,FALSE) -> 25 | O2: =IF(Requests[[#This Row],[Age (days)]]>Requests[[#This Row],[SLA Threshold]],"Yes","No") -> No
A3: RF3658439 | B3: 44666 | C3: 44691 | D3: Closed | E3: MALLIA04 | F3: =IF(ISBLANK(C3), NETWORKDAYS(B3,TODAY()), NETWORKDAYS(B3,C3)) -> 18 | G3: PASSPORT | H3: Request: Passport Leave Behind Deck extraction Q1 2022 | I3: Report | J3: Leave Behind Deck | K3: SHAJI, GENUINE | L3: Business | M3: =VLOOKUP(Requests[[#This Row],[Ticket ID]],[2]Requests!$A$2:$D$649,4,FALSE) -> 4 - Low | N3: =VLOOKUP(Requests[[#This Row],[Priority]],'SLA Config'!$B$3:$C$6,2,FALSE) -> 25 | O3: =IF(Requests[[#This Row],[Age (days)]]>Requests[[#This Row],[SLA Threshold]],"Yes","No") -> No
A4: RF3780202 | B4: 44738 | C4: 44745 | D4: Closed | E4: DINALK01 | F4: =IF(ISBLANK(C4), NETWORKDAYS(B4,TODAY()), NETWORKDAYS(B4,C4)) -> 5 | G4: CHAMP | H4: SM Data Quality Discrepancy Report [Change Mgmt General]: GBL-C4 MARM PATIENT INSIGHTS SUPPORT | I4: Audit | J4: Service Manager RFC | K4: DIGITAL CONFIGURATION MGMT, CI DATA QUALITY | L4: Digital | M4: =VLOOKUP(Requests[[#This Row],[Ticket ID]],[2]Requests!$A$2:$D$649,4,FALSE) -> 4 - Low | N4: =VLOOKUP(Requests[[#This Row],[Priority]],'SLA Config'!$B$3:$C$6,2,FALSE) -> 25 | O4: =IF(Requests[[#This Row],[Age (days)]]>Requests[[#This Row],[SLA Threshold]],"Yes","No") -> No
A5: RF3818389 | B5: 44761 | C5: 44807 | D5: Closed | E5: SIRIVV02 | F5: =IF(ISBLANK(C5), NETWORKDAYS(B5,TODAY()), NETWORKDAYS(B5,C5)) -> 34 | G5: PASSPORT | H5: Vyndamax Patient Experience Report | Access permission for specific views | I5: User Access | J5: Information/How-To | K5: DING, MING | L5: Business | M5: =VLOOKUP(Requests[[#This Row],[Ticket ID]],[2]Requests!$A$2:$D$649,4,FALSE) -> 4 - Low | N5: =VLOOKUP(Requests[[#This Row],[Priority]],'SLA Config'!$B$3:$C$6,2,FALSE) -> 25 | O5: =IF(Requests[[#This Row],[Age (days)]]>Requests[[#This Row],[SLA Threshold]],"Yes","No") -> Yes
A6: RF3833207 | B6: 44770 | C6: 44788 | D6: Closed | E6: MALLIA04 | F6: =IF(ISBLANK(C6), NETWORKDAYS(B6,TODAY()), NETWORKDAYS(B6,C6)) -> 13 | G6: PASSPORT | H6: Leave Behind deck extract Q2 2022 | I6: Report | J6: Leave Behind Deck | K6: THANGAVEL, RAMESH | L6: Business | M6: =VLOOKUP(Requests[[#This Row],[Ticket ID]],[2]Requests!$A$2:$D$649,4,FALSE) -> 4 - Low | N6: =VLOOKUP(Requests[[#This Row],[Priority]],'SLA Config'!$B$3:$C$6,2,FALSE) -> 25 | O6: =IF(Requests[[#This Row],[Age (days)]]>Requests[[#This Row],[SLA Threshold]],"Yes","No") -> No
A7: RF3847340 | B7: 44778 | C7: 44789 | D7: Closed | E7: SIRIVV02 | F7: =IF(ISBLANK(C7), NETWORKDAYS(B7,TODAY()), NETWORKDAYS(B7,C7)) -> 8 | G7: PASSPORT | H7: Access to Vyndamax patient experience report | I7: User Access | J7: Add | K7: DING, MING | L7: Business | M7: =VLOOKUP(Requests[[#This Row],[Ticket ID]],[2]Requests!$A$2:$D$649,4,FALSE) -> 4 - Low | N7: =VLOOKUP(Requests[[#This Row],[Priority]],'SLA Config'!$B$3:$C$6,2,FALSE) -> 25 | O7: =IF(Requests[[#This Row],[Age (days)]]>Requests[[#This Row],[SLA Threshold]],"Yes","No") -> No
A8: RF3868923 | B8: 44792 | C8: 44802 | D8: Closed | E8: SIRIVV02 | F8: =IF(ISBLANK(C8), NETWORKDAYS(B8,TODAY()), NETWORKDAYS(B8,C8)) -> 7 | G8: PASSPORT | H8: Request - Need to add create new security AD- Groups for patient insights | I8: User Access | J8: Security Group | K8: DINALIS, KONSTANTINOS | L8: Digital | M8: =VLOOKUP(Requests[[#This Row],[Ticket ID]],[2]Requests!$A$2:$D$649,4,FALSE) -> 3 - Medium | N8: =VLOOKUP(Requests[[#This Row],[Priority]],'SLA Config'!$B$3:$C$6,2,FALSE) -> 15 | O8: =IF(Requests[[#This Row],[Age (days)]]>Requests[[#This Row],[SLA Threshold]],"Yes","No") -> No
A9: RF3879799 | B9: 44798 | C9: 44816 | D9: Closed | E9: SIRIVV02 | F9: =IF(ISBLANK(C9), NETWORKDAYS(B9,TODAY()), NETWORKDAYS(B9,C9)) -> 13 | G9: CHAMP | H9: Patient Point - Add two new services | I9: Enhancement | J9: Data Update | K9: TROUGHT, ALLISON | L9: Business | M9: =VLOOKUP(Requests[[#This Row],[Ticket ID]],[2]Requests!$A$2:$D$649,4,FALSE) -> 4 - Low | N9: =VLOOKUP(Requests[[#This Row],[Priority]],'SLA Config'!$B$3:$C$6,2,FALSE) -> 25 | O9: =IF(Requests[[#This Row],[Age (days)]]>Requests[[#This Row],[SLA Threshold]],"Yes","No") -> No
A10: RF3891413 | B10: 44805 | C10: 44815 | D10: Closed | E10: SIRIVV02 | F10: =IF(ISBLANK(C10), NETWORKDAYS(B10,TODAY()), NETWORKDAYS(B10,C10)) -> 7 | G10: CHAMP | H10: Request to provide access for Patient Point | I10: User Access | J10: Add | K10: TROUGHT, ALLISON | L10: Business | M10: =VLOOKUP(Requests[[#This Row],[Ticket ID]],[2]Requests!$A$2:$D$649,4,FALSE) -> 4 - Low | N10: =VLOOKUP(Requests[[#This Row],[Priority]],'SLA Config'!$B$3:$C$6,2,FALSE) -> 25 | O10: =IF(Requests[[#This Row],[Age (days)]]>Requests[[#This Row],[SLA Threshold]],"Yes","No") -> No
A11: RF3892187 | B11: 44805 | C11: 44816 | D11: Closed | E11: SIRIVV02 | F11: =IF(ISBLANK(C11), NETWORKDAYS(B11,TODAY()), NETWORKDAYS(B11,C11)) -> 8 | G11: CHAMP | H11: RM Fulfillment Ticket: Patient Insights - 20220901020530402 | I11: User Access | J11: Add | K11: NAGARAJU, SUNIL KUMAR | L11: Digital | M11: =VLOOKUP(Requests[[#This Row],[Ticket ID]],[2]Requests!$A$2:$D$649,4,FALSE) -> 4 - Low | N11: =VLOOKUP(Requests[[#This Row],[Priority]],'SLA Config'!$B$3:$C$6,2,FALSE) -> 25 | O11: =IF(Requests[[#This Row],[Age (days)]]>Requests[[#This Row],[SLA Threshold]],"Yes","No") -> No
A12: RF3892781 | B12: 44806 | C12: 44818 | D12: Closed | E12: SIRIVV02 | F12: =IF(ISBLANK(C12), NETWORKDAYS(B12,TODAY()), NETWORKDAYS(B12,C12)) -> 9 | G12: CHAMP | H12: CHAMP Access updates | I12: User Access | J12: Update permissions | K12: TROUGHT, ALLISON | L12: Business | M12: =VLOOKUP(Requests[[#This Row],[Ticket ID]],[2]Requests!$A$2:$D$649,4,FALSE) -> 4 - Low | N12: =VLOOKUP(Requests[[#This Row],[Priority]],'SLA Config'!$B$3:$C$6,2,FALSE) -> 25 | O12: =IF(Requests[[#This Row],[Age (days)]]>Requests[[#This Row],[SLA Threshold]],"Yes","No") -> No
A13: RF3893669 | B13: 44806 | C13: 44818 | D13: Closed | E13: SIRIVV02 | F13: =IF(ISBLANK(C13), NETWORKDAYS(B13,TODAY()), NETWORKDAYS(B13,C13)) -> 9 | G13: CHAMP | H13: Patient Insights - Remove Access | I13: User Access | J13: Remove | K13: TROUGHT, ALLISON | L13: Business | M13: =VLOOKUP(Requests[[#This Row],[Ticket ID]],[2]Requests!$A$2:$D$649,4,FALSE) -> 4 - Low | N13: =VLOOKUP(Requests[[#This Row],[Priority]],'SLA Config'!$B$3:$C$6,2,FALSE) -> 25 | O13: =IF(Requests[[#This Row],[Age (days)]]>Requests[[#This Row],[SLA Threshold]],"Yes","No") -> No
... A361: RF5111071 | B361: 45518 | C361: 45525 | D361: Closed | E361: BABUS32 | F361: =IF(ISBLANK(C361), NETWORKDAYS(B361,TODAY()), NETWORKDAYS(B361,C361)) -> 6 | G361: PASSPORT | H361: RM Fulfillment Ticket: Patient Insights - 20240813170036309 | I361: User Access | J361: Add | K361: HOFFNER, COREY | L361: Business | M361: =VLOOKUP(Requests[[#This Row],[Ticket ID]],[2]Requests!$A$2:$D$649,4,FALSE) -> 4 - Low | N361: =VLOOKUP(Requests[[#This Row],[Priority]],'SLA Config'!$B$3:$C$6,2,FALSE) -> 25 | O361: =IF(Requests[[#This Row],[Age (days)]]>Requests[[#This Row],[SLA Threshold]],"Yes","No") -> No
A362: RF5439801 | B362: 45722 | C362: 45747 | D362: Closed | E362: GUNDAP04 | F362: =IF(ISBLANK(C362), NETWORKDAYS(B362,TODAY()), NETWORKDAYS(B362,C362)) -> 18 | G362: PASSPORT | H362: PATIENTINSIGHTS-PROD-P&ALEGAL - New dashboard request | K362: WANG, ERIC | L362: Business | M362: =VLOOKUP(Requests[[#This Row],[Ticket ID]],[2]Requests!$A$2:$D$649,4,FALSE) -> 4 - Low | N362: =VLOOKUP(Requests[[#This Row],[Priority]],'SLA Config'!$B$3:$C$6,2,FALSE) -> 25 | O362: =IF(Requests[[#This Row],[Age (days)]]>Requests[[#This Row],[SLA Threshold]],"Yes","No") -> No
A363: RF5112494 | B363: 45518 | C363: 45542 | D363: Closed | E363: DINALK01 | F363: =IF(ISBLANK(C363), NETWORKDAYS(B363,TODAY()), NETWORKDAYS(B363,C363)) -> 18 | G363: PASSPORT | H363: Patient Insights - Enhancement Request - Patient Journey TAT update | I363: Enhancement | J363: Tableau | K363: WANG, ERIC | L363: Business | M363: =VLOOKUP(Requests[[#This Row],[Ticket ID]],[2]Requests!$A$2:$D$649,4,FALSE) -> 4 - Low | N363: =VLOOKUP(Requests[[#This Row],[Priority]],'SLA Config'!$B$3:$C$6,2,FALSE) -> 25 | O363: =IF(Requests[[#This Row],[Age (days)]]>Requests[[#This Row],[SLA Threshold]],"Yes","No") -> No
A364: RF5114035 | B364: 45519 | C364: 45542 | D364: Closed | E364: GUNDAP04 | F364: =IF(ISBLANK(C364), NETWORKDAYS(B364,TODAY()), NETWORKDAYS(B364,C364)) -> 17 | G364: CHAMP | H364: Patient Insights - Add new services in CHAMP/Patient Point | I364: Enhancement | J364: Data Update | K364: TROUGHT, ALLISON | L364: Business | M364: =VLOOKUP(Requests[[#This Row],[Ticket ID]],[2]Requests!$A$2:$D$649,4,FALSE) -> 4 - Low | N364: =VLOOKUP(Requests[[#This Row],[Priority]],'SLA Config'!$B$3:$C$6,2,FALSE) -> 25 | O364: =IF(Requests[[#This Row],[Age (days)]]>Requests[[#This Row],[SLA Threshold]],"Yes","No") -> No
A365: RF5114692 | B365: 45520 | C365: 45537 | D365: Closed | E365: DINALK01 | F365: =IF(ISBLANK(C365), NETWORKDAYS(B365,TODAY()), NETWORKDAYS(B365,C365)) -> 12 | G365: PASSPORT | H365: Patient Insights | Patient Experience & Hub Scorecard questions | I365: Report | J365: Question | K365: WANG, ERIC | L365: Business | M365: =VLOOKUP(Requests[[#This Row],[Ticket ID]],[2]Requests!$A$2:$D$649,4,FALSE) -> 4 - Low | N365: =VLOOKUP(Requests[[#This Row],[Priority]],'SLA Config'!$B$3:$C$6,2,FALSE) -> 25 | O365: =IF(Requests[[#This Row],[Age (days)]]>Requests[[#This Row],[SLA Threshold]],"Yes","No") -> No
A366: RF5116312 | B366: 45523 | C366: 45529 | D366: Closed | E366: MALLIA04 | F366: =IF(ISBLANK(C366), NETWORKDAYS(B366,TODAY()), NETWORKDAYS(B366,C366)) -> 5 | G366: PASSPORT | H366: Patient Insights | Authorized for therapy update date - to ingest latest data for Velsipity brand activity | I366: Enhancement | J366: Data Update | K366: DINALIS, KONSTANTINOS | L366: Support | M366: =VLOOKUP(Requests[[#This Row],[Ticket ID]],[2]Requests!$A$2:$D$649,4,FALSE) -> 4 - Low | N366: =VLOOKUP(Requests[[#This Row],[Priority]],'SLA Config'!$B$3:$C$6,2,FALSE) -> 25 | O366: =IF(Requests[[#This Row],[Age (days)]]>Requests[[#This Row],[SLA Threshold]],"Yes","No") -> No
A367: RF5124006 | B367: 45526 | C367: 45535 | D367: Closed | E367: MALLIA04 | F367: =IF(ISBLANK(C367), NETWORKDAYS(B367,TODAY()), NETWORKDAYS(B367,C367)) -> 7 | G367: CHAMP | H367: Patient Insights | Insert data into XREF table - SPP v 867 | I367: Enhancement | J367: Data Update | K367: ANANTHAKRISHNAN, MAHADEVAN | L367: Digital | M367: =VLOOKUP(Requests[[#This Row],[Ticket ID]],[2]Requests!$A$2:$D$649,4,FALSE) -> 3 - Medium | N367: =VLOOKUP(Requests[[#This Row],[Priority]],'SLA Config'!$B$3:$C$6,2,FALSE) -> 15 | O367: =IF(Requests[[#This Row],[Age (days)]]>Requests[[#This Row],[SLA Threshold]],"Yes","No") -> No
A368: RF5132117 | B368: 45531 | C368: 45558 | D368: Closed | E368: DINALK01 | F368: =IF(ISBLANK(C368), NETWORKDAYS(B368,TODAY()), NETWORKDAYS(B368,C368)) -> 20 | G368: PASSPORT | H368: PI Hub Scorecard - Vyndalink Interim Care case/subcase type mapping | I368: Enhancement | J368: Tableau | K368: WANG, ERIC | L368: Business | M368: =VLOOKUP(Requests[[#This Row],[Ticket ID]],[2]Requests!$A$2:$D$649,4,FALSE) -> 4 - Low | N368: =VLOOKUP(Requests[[#This Row],[Priority]],'SLA Config'!$B$3:$C$6,2,FALSE) -> 25 | O368: =IF(Requests[[#This Row],[Age (days)]]>Requests[[#This Row],[SLA Threshold]],"Yes","No") -> No
A369: RF5133885 | B369: 45532 | C369: 45532 | D369: Closed | E369: MALLIA04 | F369: =IF(ISBLANK(C369), NETWORKDAYS(B369,TODAY()), NETWORKDAYS(B369,C369)) -> 1 | G369: PASSPORT | H369: Patient Insights - Hub Scorecard - Interim Care Program mapping | I369: Enhancement | J369: Tableau | K369: WANG, ERIC | L369: Business | M369: =VLOOKUP(Requests[[#This Row],[Ticket ID]],[2]Requests!$A$2:$D$649,4,FALSE) -> 4 - Low | N369: =VLOOKUP(Requests[[#This Row],[Priority]],'SLA Config'!$B$3:$C$6,2,FALSE) -> 25 | O369: =IF(Requests[[#This Row],[Age (days)]]>Requests[[#This Row],[SLA Threshold]],"Yes","No") -> No
A370: RF5134821 | B370: 45532 | C370: 45543 | D370: Closed | E370: BABUS32 | F370: =IF(ISBLANK(C370), NETWORKDAYS(B370,TODAY()), NETWORKDAYS(B370,C370)) -> 8 | G370: CHAMP | H370: Patient Point - Notification question when updating contract or services | I370: Report | J370: Question | K370: TROUGHT, ALLISON | L370: Business | M370: =VLOOKUP(Requests[[#This Row],[Ticket ID]],[2]Requests!$A$2:$D$649,4,FALSE) -> 4 - Low | N370: =VLOOKUP(Requests[[#This Row],[Priority]],'SLA Config'!$B$3:$C$6,2,FALSE) -> 25 | O370: =IF(Requests[[#This Row],[Age (days)]]>Requests[[#This Row],[SLA Threshold]],"Yes","No") -> No
A371: RF5136257 | B371: 45533 | C371: 45553 | D371: Closed | E371: GUNDAP04 | F371: =IF(ISBLANK(C371), NETWORKDAYS(B371,TODAY()), NETWORKDAYS(B371,C371)) -> 15 | G371: CHAMP | H371: Patient Insights - Add new SPP | I371: Enhancement | J371: Data Update | K371: TROUGHT, ALLISON | L371: Business | M371: =VLOOKUP(Requests[[#This Row],[Ticket ID]],[2]Requests!$A$2:$D$649,4,FALSE) -> 4 - Low | N371: =VLOOKUP(Requests[[#This Row],[Priority]],'SLA Config'!$B$3:$C$6,2,FALSE) -> 25 | O371: =IF(Requests[[#This Row],[Age (days)]]>Requests[[#This Row],[SLA Threshold]],"Yes","No") -> No
A372: RF5139954 | B372: 45537 | C372: 45578 | D372: Closed | E372: GUNDAP04 | F372: =IF(ISBLANK(C372), NETWORKDAYS(B372,TODAY()), NETWORKDAYS(B372,C372)) -> 30 | G372: PASSPORT | H372: RM Fulfillment Ticket: Patient Insights - 20240827224946838 | I372: User Access | J372: Add | K372: DILOLLO, STEVEN BERTRAND | L372: Business | M372: =VLOOKUP(Requests[[#This Row],[Ticket ID]],[2]Requests!$A$2:$D$649,4,FALSE) -> 4 - Low | N372: =VLOOKUP(Requests[[#This Row],[Priority]],'SLA Config'!$B$3:$C$6,2,FALSE) -> 25 | O372: =IF(Requests[[#This Row],[Age (days)]]>Requests[[#This Row],[SLA Threshold]],"Yes","No") -> Yes
A373: RF5139955 | B373: 45537 | C373: 45577 | D373: Closed | E373: GUNDAP04 | F373: =IF(ISBLANK(C373), NETWORKDAYS(B373,TODAY()), NETWORKDAYS(B373,C373)) -> 30 | G373: PASSPORT | H373: RM Fulfillment Ticket: Patient Insights - 20240827224811836 | I373: User Access | J373: Add | K373: WATKINS, NATALIE MARY | L373: Business | M373: =VLOOKUP(Requests[[#This Row],[Ticket ID]],[2]Requests!$A$2:$D$649,4,FALSE) -> 4 - Low | N373: =VLOOKUP(Requests[[#This Row],[Priority]],'SLA Config'!$B$3:$C$6,2,FALSE) -> 25 | O373: =IF(Requests[[#This Row],[Age (days)]]>Requests[[#This Row],[SLA Threshold]],"Yes","No") -> Yes
A374: RF5139956 | B374: 45537 | C374: 45578 | D374: Closed | E374: GUNDAP04 | F374: =IF(ISBLANK(C374), NETWORKDAYS(B374,TODAY()), NETWORKDAYS(B374,C374)) -> 30 | G374: PASSPORT | H374: RM Fulfillment Ticket: Patient Insights - 20240827224328833 | I374: User Access | J374: Add | K374: BROADUS, ALEXANDRA LAMBERT | L374: Business | M374: =VLOOKUP(Requests[[#This Row],[Ticket ID]],[2]Requests!$A$2:$D$649,4,FALSE) -> 4 - Low | N374: =VLOOKUP(Requests[[#This Row],[Priority]],'SLA Config'!$B$3:$C$6,2,FALSE) -> 25 | O374: =IF(Requests[[#This Row],[Age (days)]]>Requests[[#This Row],[SLA Threshold]],"Yes","No") -> Yes
... A424: RF5256886 | B424: 45604 | C424: 45622 | D424: Closed | E424: BABUS32 | F424: =IF(ISBLANK(C424), NETWORKDAYS(B424,TODAY()), NETWORKDAYS(B424,C424)) -> 13 | G424: PASSPORT | H424: RM Fulfillment Ticket: Patient Insights - 20241107154250767 | I424: User Access | J424: Add | K424: HULL, MICHAEL ROBERT | L424: Business | M424: =VLOOKUP(Requests[[#This Row],[Ticket ID]],[2]Requests!$A$2:$D$649,4,FALSE) -> 4 - Low | N424: =VLOOKUP(Requests[[#This Row],[Priority]],'SLA Config'!$B$3:$C$6,2,FALSE) -> 25 | O424: =IF(Requests[[#This Row],[Age (days)]]>Requests[[#This Row],[SLA Threshold]],"Yes","No") -> No
A425: RF5257332 | B425: 45604 | C425: 45613 | D425: Closed | F425: =IF(ISBLANK(C425), NETWORKDAYS(B425,TODAY()), NETWORKDAYS(B425,C425)) -> 6 | G425: PASSPORT | H425: Patient Insights | Vyndamax Target List Manual Upload to Stage and Dev | I425: Enhancement | J425: Data Update | K425: PARAMESWARAN, KARTHIGA | L425: Digital | M425: =VLOOKUP(Requests[[#This Row],[Ticket ID]],[2]Requests!$A$2:$D$649,4,FALSE) -> 4 - Low | N425: =VLOOKUP(Requests[[#This Row],[Priority]],'SLA Config'!$B$3:$C$6,2,FALSE) -> 25 | O425: =IF(Requests[[#This Row],[Age (days)]]>Requests[[#This Row],[SLA Threshold]],"Yes","No") -> No
A426: RF5259075 | B426: 45605 | C426: 45612 | D426: Closed | E426: DINALK01 | F426: =IF(ISBLANK(C426), NETWORKDAYS(B426,TODAY()), NETWORKDAYS(B426,C426)) -> 5 | G426: CONFIGURATION MANAGEMENT | H426: SM Data Quality Discrepancy Report [Change Mgmt General]: GBL-C4 MARM PATIENT INSIGHTS SUPPORT | K426: DIGITAL CONFIGURATION MGMT, CI DATA QUALITY | L426: Digital | M426: =VLOOKUP(Requests[[#This Row],[Ticket ID]],[2]Requests!$A$2:$D$649,4,FALSE) -> 4 - Low | N426: =VLOOKUP(Requests[[#This Row],[Priority]],'SLA Config'!$B$3:$C$6,2,FALSE) -> 25 | O426: =IF(Requests[[#This Row],[Age (days)]]>Requests[[#This Row],[SLA Threshold]],"Yes","No") -> No
A427: RF5260440 | B427: 45607 | C427: 45620 | D427: Closed | E427: BABUS32 | F427: =IF(ISBLANK(C427), NETWORKDAYS(B427,TODAY()), NETWORKDAYS(B427,C427)) -> 10 | G427: PASSPORT | H427: RM Fulfillment Ticket: Patient Insights - 20241111025632846 | K427: DINALIS, KONSTANTINOS | L427: Digital | M427: =VLOOKUP(Requests[[#This Row],[Ticket ID]],[2]Requests!$A$2:$D$649,4,FALSE) -> 4 - Low | N427: =VLOOKUP(Requests[[#This Row],[Priority]],'SLA Config'!$B$3:$C$6,2,FALSE) -> 25 | O427: =IF(Requests[[#This Row],[Age (days)]]>Requests[[#This Row],[SLA Threshold]],"Yes","No") -> No
A428: RF5260442 | B428: 45607 | C428: 45620 | D428: Closed | E428: BABUS32 | F428: =IF(ISBLANK(C428), NETWORKDAYS(B428,TODAY()), NETWORKDAYS(B428,C428)) -> 10 | G428: PASSPORT | H428: RM Fulfillment Ticket: Patient Insights - 20241111025539841 | K428: DINALIS, KONSTANTINOS | L428: Digital | M428: =VLOOKUP(Requests[[#This Row],[Ticket ID]],[2]Requests!$A$2:$D$649,4,FALSE) -> 4 - Low | N428: =VLOOKUP(Requests[[#This Row],[Priority]],'SLA Config'!$B$3:$C$6,2,FALSE) -> 25 | O428: =IF(Requests[[#This Row],[Age (days)]]>Requests[[#This Row],[SLA Threshold]],"Yes","No") -> No
A429: RF5260443 | B429: 45607 | C429: 45623 | D429: Closed | E429: BABUS32 | F429: =IF(ISBLANK(C429), NETWORKDAYS(B429,TODAY()), NETWORKDAYS(B429,C429)) -> 13 | G429: PASSPORT | H429: RM Fulfillment Ticket: Patient Insights - 20241111025720850 | K429: DINALIS, KONSTANTINOS | L429: Digital | M429: =VLOOKUP(Requests[[#This Row],[Ticket ID]],[2]Requests!$A$2:$D$649,4,FALSE) -> 4 - Low | N429: =VLOOKUP(Requests[[#This Row],[Priority]],'SLA Config'!$B$3:$C$6,2,FALSE) -> 25 | O429: =IF(Requests[[#This Row],[Age (days)]]>Requests[[#This Row],[SLA Threshold]],"Yes","No") -> No
A430: RF5260254 | B430: 45607 | C430: 45628 | D430: Closed | E430: BABUS32 | F430: =IF(ISBLANK(C430), NETWORKDAYS(B430,TODAY()), NETWORKDAYS(B430,C430)) -> 16 | G430: PASSPORT | H430: RM Fulfillment Ticket: Patient Insights - 20241111025950857 | K430: DINALIS, KONSTANTINOS | L430: Digital | M430: =VLOOKUP(Requests[[#This Row],[Ticket ID]],[2]Requests!$A$2:$D$649,4,FALSE) -> 4 - Low | N430: =VLOOKUP(Requests[[#This Row],[Priority]],'SLA Config'!$B$3:$C$6,2,FALSE) -> 25 | O430: =IF(Requests[[#This Row],[Age (days)]]>Requests[[#This Row],[SLA Threshold]],"Yes","No") -> No
A431: RF5261823 | B431: 45608 | C431: 45664 | D431: Closed | E431: GUNDAP04 | F431: =IF(ISBLANK(C431), NETWORKDAYS(B431,TODAY()), NETWORKDAYS(B431,C431)) -> 41 | G431: PASSPORT | H431: Patient Insights | Create new group "MASPA DTR" | K431: WANG, ERIC | L431: Business | M431: =VLOOKUP(Requests[[#This Row],[Ticket ID]],[2]Requests!$A$2:$D$649,4,FALSE) -> 4 - Low | N431: =VLOOKUP(Requests[[#This Row],[Priority]],'SLA Config'!$B$3:$C$6,2,FALSE) -> 25 | O431: =IF(Requests[[#This Row],[Age (days)]]>Requests[[#This Row],[SLA Threshold]],"Yes","No") -> Yes
A432: RF5266697 | B432: 45610 | C432: 45615 | D432: Closed | E432: BABUS32 | F432: =IF(ISBLANK(C432), NETWORKDAYS(B432,TODAY()), NETWORKDAYS(B432,C432)) -> 4 | G432: PASSPORT | H432: Patient Insights | Vyndamax Target List Manual Table Creation | K432: PATRO, P SAURAV KUMAR | L432: Digital | M432: =VLOOKUP(Requests[[#This Row],[Ticket ID]],[2]Requests!$A$2:$D$649,4,FALSE) -> 4 - Low | N432: =VLOOKUP(Requests[[#This Row],[Priority]],'SLA Config'!$B$3:$C$6,2,FALSE) -> 25 | O432: =IF(Requests[[#This Row],[Age (days)]]>Requests[[#This Row],[SLA Threshold]],"Yes","No") -> No
A433: RF5270185 | B433: 45611 | C433: 45634 | D433: Closed | E433: GUNDAP04 | F433: =IF(ISBLANK(C433), NETWORKDAYS(B433,TODAY()), NETWORKDAYS(B433,C433)) -> 16 | G433: PASSPORT | H433: Patient Insights - User activity statistics | K433: KARDI, PANDE PUTU ADYSTI | L433: Digital | M433: =VLOOKUP(Requests[[#This Row],[Ticket ID]],[2]Requests!$A$2:$D$649,4,FALSE) -> 4 - Low | N433: =VLOOKUP(Requests[[#This Row],[Priority]],'SLA Config'!$B$3:$C$6,2,FALSE) -> 25 | O433: =IF(Requests[[#This Row],[Age (days)]]>Requests[[#This Row],[SLA Threshold]],"Yes","No") -> No
A434: RF5272763 | B434: 45614 | C434: 45633 | D434: Closed | E434: GUNDAP04 | F434: =IF(ISBLANK(C434), NETWORKDAYS(B434,TODAY()), NETWORKDAYS(B434,C434)) -> 15 | G434: PASSPORT | H434: Patient Insights - Number of dashboard views | K434: KARDI, PANDE PUTU ADYSTI | L434: Digital | M434: =VLOOKUP(Requests[[#This Row],[Ticket ID]],[2]Requests!$A$2:$D$649,4,FALSE) -> 4 - Low | N434: =VLOOKUP(Requests[[#This Row],[Priority]],'SLA Config'!$B$3:$C$6,2,FALSE) -> 25 | O434: =IF(Requests[[#This Row],[Age (days)]]>Requests[[#This Row],[SLA Threshold]],"Yes","No") -> No
A435: RF5260253 | B435: 45607 | C435: 45620 | D435: Closed | E435: BABUS32 | F435: =IF(ISBLANK(C435), NETWORKDAYS(B435,TODAY()), NETWORKDAYS(B435,C435)) -> 10 | G435: PASSPORT | H435: RM Fulfillment Ticket: Patient Insights - 20241111030044858 | K435: DINALIS, KONSTANTINOS | L435: Support | M435: =VLOOKUP(Requests[[#This Row],[Ticket ID]],[2]Requests!$A$2:$D$649,4,FALSE) -> 4 - Low | N435: =VLOOKUP(Requests[[#This Row],[Priority]],'SLA Config'!$B$3:$C$6,2,FALSE) -> 25 | O435: =IF(Requests[[#This Row],[Age (days)]]>Requests[[#This Row],[SLA Threshold]],"Yes","No") -> No
A436: RF5278190 | B436: 45617 | C436: 45627 | D436: Closed | E436: DINALK01 | F436: =IF(ISBLANK(C436), NETWORKDAYS(B436,TODAY()), NETWORKDAYS(B436,C436)) -> 7 | G436: PASSPORT | H436: Patient Insights | AMBA data extract | K436: GOLDSMITH, GEORGE | L436: Business | M436: =VLOOKUP(Requests[[#This Row],[Ticket ID]],[2]Requests!$A$2:$D$649,4,FALSE) -> 3 - Medium | N436: =VLOOKUP(Requests[[#This Row],[Priority]],'SLA Config'!$B$3:$C$6,2,FALSE) -> 15 | O436: =IF(Requests[[#This Row],[Age (days)]]>Requests[[#This Row],[SLA Threshold]],"Yes","No") -> No
A437: RF5281223 | B437: 45618 | C437: 45629 | D437: Closed | E437: MALLIA04 | F437: =IF(ISBLANK(C437), NETWORKDAYS(B437,TODAY()), NETWORKDAYS(B437,C437)) -> 8 | G437: CHAMP | H437: Patient Insights - Onco360 SPIF extract | K437: TROUGHT, ALLISON | L437: Business | M437: =VLOOKUP(Requests[[#This Row],[Ticket ID]],[2]Requests!$A$2:$D$649,4,FALSE) -> 4 - Low | N437: =VLOOKUP(Requests[[#This Row],[Priority]],'SLA Config'!$B$3:$C$6,2,FALSE) -> 25 | O437: =IF(Requests[[#This Row],[Age (days)]]>Requests[[#This Row],[SLA Threshold]],"Yes","No") -> No
... A445: RF5306838 | B445: 45636 | C445: 45661 | D445: Closed | E445: GUNDAP04 | F445: =IF(ISBLANK(C445), NETWORKDAYS(B445,TODAY()), NETWORKDAYS(B445,C445)) -> 19 | G445: PASSPORT | H445: Patient Insights - Revoke Access for Kostas | K445: GUNDANNA, PUNYA | L445: Support | M445: =VLOOKUP(Requests[[#This Row],[Ticket ID]],[2]Requests!$A$2:$D$649,4,FALSE) -> 4 - Low | N445: =VLOOKUP(Requests[[#This Row],[Priority]],'SLA Config'!$B$3:$C$6,2,FALSE) -> 25 | O445: =IF(Requests[[#This Row],[Age (days)]]>Requests[[#This Row],[SLA Threshold]],"Yes","No") -> No
A446: RF5307788 | B446: 45637 | C446: 45651 | D446: Closed | E446: BABUS32 | F446: =IF(ISBLANK(C446), NETWORKDAYS(B446,TODAY()), NETWORKDAYS(B446,C446)) -> 11 | G446: PASSPORT | H446: Patient Insights - Patient Insights access to new joiner in DevSecOps team | K446: GAFFOR, ABDUL RAHMAN | M446: =VLOOKUP(Requests[[#This Row],[Ticket ID]],[2]Requests!$A$2:$D$649,4,FALSE) -> 4 - Low | N446: =VLOOKUP(Requests[[#This Row],[Priority]],'SLA Config'!$B$3:$C$6,2,FALSE) -> 25 | O446: =IF(Requests[[#This Row],[Age (days)]]>Requests[[#This Row],[SLA Threshold]],"Yes","No") -> No
A447: RF5307380 | B447: 45636 | C447: 45668 | D447: Closed | E447: MALLIA04 | F447: =IF(ISBLANK(C447), NETWORKDAYS(B447,TODAY()), NETWORKDAYS(B447,C447)) -> 24 | G447: CHAMP | H447: Patient Insights - data extract for Senderra for 2Q and 3Q | K447: STEPHENS, TAMEKA | L447: Business | M447: =VLOOKUP(Requests[[#This Row],[Ticket ID]],[2]Requests!$A$2:$D$649,4,FALSE) -> 4 - Low | N447: =VLOOKUP(Requests[[#This Row],[Priority]],'SLA Config'!$B$3:$C$6,2,FALSE) -> 25 | O447: =IF(Requests[[#This Row],[Age (days)]]>Requests[[#This Row],[SLA Threshold]],"Yes","No") -> No
A448: RF5307382 | B448: 45636 | C448: 45668 | D448: Closed | E448: MALLIA04 | F448: =IF(ISBLANK(C448), NETWORKDAYS(B448,TODAY()), NETWORKDAYS(B448,C448)) -> 24 | G448: CHAMP | H448: Patient Insights - SPIF raw data extract for Lumicera for 2Q and 3Q. | K448: STEPHENS, TAMEKA | L448: Business | M448: =VLOOKUP(Requests[[#This Row],[Ticket ID]],[2]Requests!$A$2:$D$649,4,FALSE) -> 4 - Low | N448: =VLOOKUP(Requests[[#This Row],[Priority]],'SLA Config'!$B$3:$C$6,2,FALSE) -> 25 | O448: =IF(Requests[[#This Row],[Age (days)]]>Requests[[#This Row],[SLA Threshold]],"Yes","No") -> No
A449: RF5456139 | B449: 45733 | C449: 45747 | D449: Closed | E449: DURGAA02 | F449: =IF(ISBLANK(C449), NETWORKDAYS(B449,TODAY()), NETWORKDAYS(B449,C449)) -> 11 | G449: PASSPORT | H449: Patient Insights | Dual RFC created to deploy Polaris customer engagement data into a table for Prod. | K449: DURGAM, AKHIL | L449: Support | M449: =VLOOKUP(Requests[[#This Row],[Ticket ID]],[2]Requests!$A$2:$D$649,4,FALSE) -> 4 - Low | N449: =VLOOKUP(Requests[[#This Row],[Priority]],'SLA Config'!$B$3:$C$6,2,FALSE) -> 25 | O449: =IF(Requests[[#This Row],[Age (days)]]>Requests[[#This Row],[SLA Threshold]],"Yes","No") -> No
A450: RF5310776 | B450: 45638 | C450: 45669 | D450: Closed | E450: BABUS32 | F450: =IF(ISBLANK(C450), NETWORKDAYS(B450,TODAY()), NETWORKDAYS(B450,C450)) -> 22 | G450: PASSPORT | H450: PatientInsight access - atharva.raut@pfizer.com | K450: PENG, XIAO JIANG | L450: Support | M450: =VLOOKUP(Requests[[#This Row],[Ticket ID]],[2]Requests!$A$2:$D$649,4,FALSE) -> 3 - Medium | N450: =VLOOKUP(Requests[[#This Row],[Priority]],'SLA Config'!$B$3:$C$6,2,FALSE) -> 15 | O450: =IF(Requests[[#This Row],[Age (days)]]>Requests[[#This Row],[SLA Threshold]],"Yes","No") -> Yes
A451: RF5312509 | B451: 45639 | C451: 45693 | D451: Closed | E451: PENGX35 | F451: =IF(ISBLANK(C451), NETWORKDAYS(B451,TODAY()), NETWORKDAYS(B451,C451)) -> 39 | G451: OTHER | H451: RM & Patient Service CMDB CI Remediation | GBL-C4 MARM PATIENT INSIGHTS SUPPORT | K451: SEETHARAMAN, SRIDHAR | M451: =VLOOKUP(Requests[[#This Row],[Ticket ID]],[2]Requests!$A$2:$D$649,4,FALSE) -> 4 - Low | N451: =VLOOKUP(Requests[[#This Row],[Priority]],'SLA Config'!$B$3:$C$6,2,FALSE) -> 25 | O451: =IF(Requests[[#This Row],[Age (days)]]>Requests[[#This Row],[SLA Threshold]],"Yes","No") -> Yes
A452: RF5311856 | B452: 45639 | C452: 45669 | D452: Closed | E452: GUNDAP04 | F452: =IF(ISBLANK(C452), NETWORKDAYS(B452,TODAY()), NETWORKDAYS(B452,C452)) -> 21 | G452: CHAMP | H452: Patient Insights - we need to request PSSP everymonth for that vyndamax engagement data | K452: MALLIKARJUN INGALALLI, ANUPAMA | L452: Support | M452: =VLOOKUP(Requests[[#This Row],[Ticket ID]],[2]Requests!$A$2:$D$649,4,FALSE) -> 4 - Low | N452: =VLOOKUP(Requests[[#This Row],[Priority]],'SLA Config'!$B$3:$C$6,2,FALSE) -> 25 | O452: =IF(Requests[[#This Row],[Age (days)]]>Requests[[#This Row],[SLA Threshold]],"Yes","No") -> No
A453: RF5301619 | B453: 45632 | C453: 45668 | D453: Closed | E453: BABUS32 | F453: =IF(ISBLANK(C453), NETWORKDAYS(B453,TODAY()), NETWORKDAYS(B453,C453)) -> 26 | G453: PASSPORT | H453: RM Fulfillment Ticket: Patient Insights - 20241205133629226 | K453: TROUGHT, ALLISON | L453: Business | M453: =VLOOKUP(Requests[[#This Row],[Ticket ID]],[2]Requests!$A$2:$D$649,4,FALSE) -> 4 - Low | N453: =VLOOKUP(Requests[[#This Row],[Priority]],'SLA Config'!$B$3:$C$6,2,FALSE) -> 25 | O453: =IF(Requests[[#This Row],[Age (days)]]>Requests[[#This Row],[SLA Threshold]],"Yes","No") -> Yes
A454: RF5308951 | B454: 45637 | C454: 45668 | D454: Closed | E454: BABUS32 | F454: =IF(ISBLANK(C454), NETWORKDAYS(B454,TODAY()), NETWORKDAYS(B454,C454)) -> 23 | G454: PASSPORT | H454: RM Fulfillment Ticket: Patient Insights - 20241211102644161 | K454: TROUGHT, ALLISON | L454: Business | M454: =VLOOKUP(Requests[[#This Row],[Ticket ID]],[2]Requests!$A$2:$D$649,4,FALSE) -> 4 - Low | N454: =VLOOKUP(Requests[[#This Row],[Priority]],'SLA Config'!$B$3:$C$6,2,FALSE) -> 25 | O454: =IF(Requests[[#This Row],[Age (days)]]>Requests[[#This Row],[SLA Threshold]],"Yes","No") -> No
A455: RF5308950 | B455: 45637 | C455: 45672 | D455: Closed | E455: BABUS32 | F455: =IF(ISBLANK(C455), NETWORKDAYS(B455,TODAY()), NETWORKDAYS(B455,C455)) -> 26 | G455: PASSPORT | H455: RM Fulfillment Ticket: Patient Insights - 20241211102332144 | K455: TROUGHT, ALLISON | L455: Business | M455: =VLOOKUP(Requests[[#This Row],[Ticket ID]],[2]Requests!$A$2:$D$649,4,FALSE) -> 4 - Low | N455: =VLOOKUP(Requests[[#This Row],[Priority]],'SLA Config'!$B$3:$C$6,2,FALSE) -> 25 | O455: =IF(Requests[[#This Row],[Age (days)]]>Requests[[#This Row],[SLA Threshold]],"Yes","No") -> Yes
A456: RF5308952 | B456: 45637 | C456: 45668 | D456: Closed | E456: BABUS32 | F456: =IF(ISBLANK(C456), NETWORKDAYS(B456,TODAY()), NETWORKDAYS(B456,C456)) -> 23 | G456: PASSPORT | H456: RM Fulfillment Ticket: Patient Insights - 20241211102507150 | K456: TROUGHT, ALLISON | L456: Business | M456: =VLOOKUP(Requests[[#This Row],[Ticket ID]],[2]Requests!$A$2:$D$649,4,FALSE) -> 4 - Low | N456: =VLOOKUP(Requests[[#This Row],[Priority]],'SLA Config'!$B$3:$C$6,2,FALSE) -> 25 | O456: =IF(Requests[[#This Row],[Age (days)]]>Requests[[#This Row],[SLA Threshold]],"Yes","No") -> No
A457: RF5307767 | B457: 45637 | C457: 45693 | D457: Closed | E457: GUNDAP04 | F457: =IF(ISBLANK(C457), NETWORKDAYS(B457,TODAY()), NETWORKDAYS(B457,C457)) -> 41 | G457: PASSPORT | H457: Patient Insights - Pedro Garcia (pedro.garcia@pfizer.com) to the PATIENTINSIGHTS-PROD-SAS-OPS | K457: WANG, ERIC | L457: Business | M457: =VLOOKUP(Requests[[#This Row],[Ticket ID]],[2]Requests!$A$2:$D$649,4,FALSE) -> 4 - Low | N457: =VLOOKUP(Requests[[#This Row],[Priority]],'SLA Config'!$B$3:$C$6,2,FALSE) -> 25 | O457: =IF(Requests[[#This Row],[Age (days)]]>Requests[[#This Row],[SLA Threshold]],"Yes","No") -> Yes
A458: RF5350211 | B458: 45669 | C458: 45675 | D458: Closed | E458: BABUS32 | F458: =IF(ISBLANK(C458), NETWORKDAYS(B458,TODAY()), NETWORKDAYS(B458,C458)) -> 5 | G458: PASSPORT | H458: Request-Diaz-Lacayo, Freddy | K458: DIAZ-LACAYO, FREDDY | M458: =VLOOKUP(Requests[[#This Row],[Ticket ID]],[2]Requests!$A$2:$D$649,4,FALSE) -> 4 - Low | N458: =VLOOKUP(Requests[[#This Row],[Priority]],'SLA Config'!$B$3:$C$6,2,FALSE) -> 25 | O458: =IF(Requests[[#This Row],[Age (days)]]>Requests[[#This Row],[SLA Threshold]],"Yes","No") -> No
A459: RF5335226 | B459: 45660 | C459: 45675 | D459: Closed | E459: GUNDAP04 | F459: =IF(ISBLANK(C459), NETWORKDAYS(B459,TODAY()), NETWORKDAYS(B459,C459)) -> 11 | G459: PASSPORT | H459: Patient Insights - Revoke Access for Ramesh Ganji from patient insights account | K459: GUNDANNA, PUNYA | L459: Support | M459: =VLOOKUP(Requests[[#This Row],[Ticket ID]],[2]Requests!$A$2:$D$649,4,FALSE) -> 4 - Low | N459: =VLOOKUP(Requests[[#This Row],[Priority]],'SLA Config'!$B$3:$C$6,2,FALSE) -> 25 | O459: =IF(Requests[[#This Row],[Age (days)]]>Requests[[#This Row],[SLA Threshold]],"Yes","No") -> No
A460: RF5339489 | B460: 45663 | C460: 45678 | D460: Closed | E460: BABUS32 | F460: =IF(ISBLANK(C460), NETWORKDAYS(B460,TODAY()), NETWORKDAYS(B460,C460)) -> 12 | G460: PASSPORT | H460: assign Patient Insight access to Shailesh.More@pfizer.com | K460: PENG, XIAO JIANG | L460: Support | M460: =VLOOKUP(Requests[[#This Row],[Ticket ID]],[2]Requests!$A$2:$D$649,4,FALSE) -> 4 - Low | N460: =VLOOKUP(Requests[[#This Row],[Priority]],'SLA Config'!$B$3:$C$6,2,FALSE) -> 25 | O460: =IF(Requests[[#This Row],[Age (days)]]>Requests[[#This Row],[SLA Threshold]],"Yes","No") -> No
A461: RF5340856 | B461: 45664 | C461: 45693 | D461: Closed | E461: GUNDAP04 | F461: =IF(ISBLANK(C461), NETWORKDAYS(B461,TODAY()), NETWORKDAYS(B461,C461)) -> 22 | G461: PASSPORT | H461: Patient Insight - upcoming Tableau Cloud Migration and Dev Cleaning | K461: GUNDANNA, PUNYA | L461: Support | M461: =VLOOKUP(Requests[[#This Row],[Ticket ID]],[2]Requests!$A$2:$D$649,4,FALSE) -> 4 - Low | N461: =VLOOKUP(Requests[[#This Row],[Priority]],'SLA Config'!$B$3:$C$6,2,FALSE) -> 25 | O461: =IF(Requests[[#This Row],[Age (days)]]>Requests[[#This Row],[SLA Threshold]],"Yes","No") -> No
A462: RF5340954 | B462: 45664 | C462: 45689 | D462: Closed | E462: ANANDA40 | F462: =IF(ISBLANK(C462), NETWORKDAYS(B462,TODAY()), NETWORKDAYS(B462,C462)) -> 19 | G462: PASSPORT | H462: Patient Insights | Retire RHEL 7 servers | K462: ANAND, ASHISH | L462: Support | M462: =VLOOKUP(Requests[[#This Row],[Ticket ID]],[2]Requests!$A$2:$D$649,4,FALSE) -> 4 - Low | N462: =VLOOKUP(Requests[[#This Row],[Priority]],'SLA Config'!$B$3:$C$6,2,FALSE) -> 25 | O462: =IF(Requests[[#This Row],[Age (days)]]>Requests[[#This Row],[SLA Threshold]],"Yes","No") -> No
A463: RF5468097 | B463: 45740 | C463: 45747 | D463: Closed | E463: ANANDA40 | F463: =IF(ISBLANK(C463), NETWORKDAYS(B463,TODAY()), NETWORKDAYS(B463,C463)) -> 6 | G463: POLARIS | H463: Patient Insights | Data Refresh | UAT Environment | K463: ANAND, ASHISH | L463: Support | M463: =VLOOKUP(Requests[[#This Row],[Ticket ID]],[2]Requests!$A$2:$D$649,4,FALSE) -> 4 - Low | N463: =VLOOKUP(Requests[[#This Row],[Priority]],'SLA Config'!$B$3:$C$6,2,FALSE) -> 25 | O463: =IF(Requests[[#This Row],[Age (days)]]>Requests[[#This Row],[SLA Threshold]],"Yes","No") -> No
A464: RF5342686 | B464: 45665 | C464: 45678 | D464: Closed | E464: BABUS32 | F464: =IF(ISBLANK(C464), NETWORKDAYS(B464,TODAY()), NETWORKDAYS(B464,C464)) -> 10 | G464: PASSPORT | H464: Patient Insights | Access to Patient Experience: Velsipity addition for Damien | K464: WANG, ERIC | L464: Business | M464: =VLOOKUP(Requests[[#This Row],[Ticket ID]],[2]Requests!$A$2:$D$649,4,FALSE) -> 4 - Low | N464: =VLOOKUP(Requests[[#This Row],[Priority]],'SLA Config'!$B$3:$C$6,2,FALSE) -> 25 | O464: =IF(Requests[[#This Row],[Age (days)]]>Requests[[#This Row],[SLA Threshold]],"Yes","No") -> No
A465: RF5342962 | B465: 45665 | C465: 45766 | D465: Closed | E465: ANANDA40 | F465: =IF(ISBLANK(C465), NETWORKDAYS(B465,TODAY()), NETWORKDAYS(B465,C465)) -> 73 | G465: PASSPORT | H465: Patient Insights | Field switch for the Primary Care FAL dashboard chart | K465: MIRANDA, CAITLIN REBECCA | L465: Digital | M465: =VLOOKUP(Requests[[#This Row],[Ticket ID]],[2]Requests!$A$2:$D$649,4,FALSE) -> 4 - Low | N465: =VLOOKUP(Requests[[#This Row],[Priority]],'SLA Config'!$B$3:$C$6,2,FALSE) -> 25 | O465: =IF(Requests[[#This Row],[Age (days)]]>Requests[[#This Row],[SLA Threshold]],"Yes","No") -> Yes
A466: RF5346409 | B466: 45666 | C466: 45703 | D466: Closed | E466: CHANDU06 | F466: =IF(ISBLANK(C466), NETWORKDAYS(B466,TODAY()), NETWORKDAYS(B466,C466)) -> 27 | G466: CHAMP | H466: Patient Insights -Year Drop Down Filter Update | K466: TROUGHT, ALLISON | L466: Business | M466: =VLOOKUP(Requests[[#This Row],[Ticket ID]],[2]Requests!$A$2:$D$649,4,FALSE) -> 4 - Low | N466: =VLOOKUP(Requests[[#This Row],[Priority]],'SLA Config'!$B$3:$C$6,2,FALSE) -> 25 | O466: =IF(Requests[[#This Row],[Age (days)]]>Requests[[#This Row],[SLA Threshold]],"Yes","No") -> Yes
A467: RF5345094 | B467: 45665 | C467: 45689 | D467: Closed | E467: ANANDA40 | F467: =IF(ISBLANK(C467), NETWORKDAYS(B467,TODAY()), NETWORKDAYS(B467,C467)) -> 18 | G467: PASSPORT | H467: Patient Insights | Update KB Article | K467: ANAND, ASHISH | L467: Support | M467: =VLOOKUP(Requests[[#This Row],[Ticket ID]],[2]Requests!$A$2:$D$649,4,FALSE) -> 4 - Low | N467: =VLOOKUP(Requests[[#This Row],[Priority]],'SLA Config'!$B$3:$C$6,2,FALSE) -> 25 | O467: =IF(Requests[[#This Row],[Age (days)]]>Requests[[#This Row],[SLA Threshold]],"Yes","No") -> No
A468: RF5355369 | B468: 45672 | C468: 45679 | D468: Closed | E468: GUNDAP04 | F468: =IF(ISBLANK(C468), NETWORKDAYS(B468,TODAY()), NETWORKDAYS(B468,C468)) -> 6 | G468: PASSPORT | H468: Patient Insight | Delete Duplicate Record | K468: GUNDANNA, PUNYA | L468: Support | M468: =VLOOKUP(Requests[[#This Row],[Ticket ID]],[2]Requests!$A$2:$D$649,4,FALSE) -> 4 - Low | N468: =VLOOKUP(Requests[[#This Row],[Priority]],'SLA Config'!$B$3:$C$6,2,FALSE) -> 25 | O468: =IF(Requests[[#This Row],[Age (days)]]>Requests[[#This Row],[SLA Threshold]],"Yes","No") -> No
A469: RF5357462 | B469: 45673 | C469: 45698 | D469: Closed | E469: GUNDAP04 | F469: =IF(ISBLANK(C469), NETWORKDAYS(B469,TODAY()), NETWORKDAYS(B469,C469)) -> 18 | G469: PASSPORT | H469: Patient Insights | Access to Hub scorecard dashboard | K469: GUNDANNA, PUNYA | L469: Support | M469: =VLOOKUP(Requests[[#This Row],[Ticket ID]],[2]Requests!$A$2:$D$649,4,FALSE) -> 4 - Low | N469: =VLOOKUP(Requests[[#This Row],[Priority]],'SLA Config'!$B$3:$C$6,2,FALSE) -> 25 | O469: =IF(Requests[[#This Row],[Age (days)]]>Requests[[#This Row],[SLA Threshold]],"Yes","No") -> No
A470: RF5462635 | B470: 45736 | C470: 45747 | D470: Closed | E470: GUNDAP04 | F470: =IF(ISBLANK(C470), NETWORKDAYS(B470,TODAY()), NETWORKDAYS(B470,C470)) -> 8 | G470: PASSPORT | H470: Patient Insights | Urgent Access request-CVS-Lance Reno | K470: DESAI, RAJ | L470: Business | M470: =VLOOKUP(Requests[[#This Row],[Ticket ID]],[2]Requests!$A$2:$D$649,4,FALSE) -> 3 - Medium | N470: =VLOOKUP(Requests[[#This Row],[Priority]],'SLA Config'!$B$3:$C$6,2,FALSE) -> 15 | O470: =IF(Requests[[#This Row],[Age (days)]]>Requests[[#This Row],[SLA Threshold]],"Yes","No") -> No
... A489: RF5380055 | B489: 45687 | C489: 45698 | D489: Closed | E489: GUNDAP04 | F489: =IF(ISBLANK(C489), NETWORKDAYS(B489,TODAY()), NETWORKDAYS(B489,C489)) -> 8 | G489: PASSPORT | H489: Patient Insights | Dominique Songa - OSOT Dashboard Access | K489: WANG, ERIC | L489: Business | M489: =VLOOKUP(Requests[[#This Row],[Ticket ID]],[2]Requests!$A$2:$D$649,4,FALSE) -> 4 - Low | N489: =VLOOKUP(Requests[[#This Row],[Priority]],'SLA Config'!$B$3:$C$6,2,FALSE) -> 25 | O489: =IF(Requests[[#This Row],[Age (days)]]>Requests[[#This Row],[SLA Threshold]],"Yes","No") -> No
A490: RF5353536 | B490: 45671 | C490: 45693 | D490: Closed | E490: BABUS32 | F490: =IF(ISBLANK(C490), NETWORKDAYS(B490,TODAY()), NETWORKDAYS(B490,C490)) -> 17 | G490: PASSPORT | H490: Request for Bernadette.Townson@pfizer.com | K490: VALLONE, BERNADETTE M | L490: #N/A | M490: =VLOOKUP(Requests[[#This Row],[Ticket ID]],[2]Requests!$A$2:$D$649,4,FALSE) -> 4 - Low | N490: =VLOOKUP(Requests[[#This Row],[Priority]],'SLA Config'!$B$3:$C$6,2,FALSE) -> 25 | O490: =IF(Requests[[#This Row],[Age (days)]]>Requests[[#This Row],[SLA Threshold]],"Yes","No") -> No
A491: RF5357490 | B491: 45673 | C491: 45693 | D491: Closed | E491: BABUS32 | F491: =IF(ISBLANK(C491), NETWORKDAYS(B491,TODAY()), NETWORKDAYS(B491,C491)) -> 15 | G491: PASSPORT | H491: Patient Insights | Patient Insights User Access request: Joseph Barone | K491: GUNDANNA, PUNYA | L491: Support | M491: =VLOOKUP(Requests[[#This Row],[Ticket ID]],[2]Requests!$A$2:$D$649,4,FALSE) -> 4 - Low | N491: =VLOOKUP(Requests[[#This Row],[Priority]],'SLA Config'!$B$3:$C$6,2,FALSE) -> 25 | O491: =IF(Requests[[#This Row],[Age (days)]]>Requests[[#This Row],[SLA Threshold]],"Yes","No") -> No
A492: RF5379032 | B492: 45686 | C492: 45712 | D492: Closed | E492: GUNDAP04 | F492: =IF(ISBLANK(C492), NETWORKDAYS(B492,TODAY()), NETWORKDAYS(B492,C492)) -> 19 | G492: CHAMP | H492: Patient Insights - Enhancement Request | K492: TROUGHT, ALLISON | L492: Business | M492: =VLOOKUP(Requests[[#This Row],[Ticket ID]],[2]Requests!$A$2:$D$649,4,FALSE) -> 4 - Low | N492: =VLOOKUP(Requests[[#This Row],[Priority]],'SLA Config'!$B$3:$C$6,2,FALSE) -> 25 | O492: =IF(Requests[[#This Row],[Age (days)]]>Requests[[#This Row],[SLA Threshold]],"Yes","No") -> No
A493: RF5397950 | B493: 45698 | C493: 45710 | D493: Closed | E493: GUNDAP04 | F493: =IF(ISBLANK(C493), NETWORKDAYS(B493,TODAY()), NETWORKDAYS(B493,C493)) -> 10 | G493: PASSPORT | H493: Patient Insights | Daijin Kim - OSOT Dashboard Access | K493: GUNDANNA, PUNYA | L493: Support | M493: =VLOOKUP(Requests[[#This Row],[Ticket ID]],[2]Requests!$A$2:$D$649,4,FALSE) -> 4 - Low | N493: =VLOOKUP(Requests[[#This Row],[Priority]],'SLA Config'!$B$3:$C$6,2,FALSE) -> 25 | O493: =IF(Requests[[#This Row],[Age (days)]]>Requests[[#This Row],[SLA Threshold]],"Yes","No") -> No
A494: RF5392361 | B494: 45694 | C494: 45713 | D494: Closed | E494: GUNDAP04 | F494: =IF(ISBLANK(C494), NETWORKDAYS(B494,TODAY()), NETWORKDAYS(B494,C494)) -> 14 | G494: PASSPORT | H494: Patient Insight | RFC for OSOT and FRM Deployment -UAT/PROD | K494: GUNDANNA, PUNYA | L494: Support | M494: =VLOOKUP(Requests[[#This Row],[Ticket ID]],[2]Requests!$A$2:$D$649,4,FALSE) -> 2 - High | N494: =VLOOKUP(Requests[[#This Row],[Priority]],'SLA Config'!$B$3:$C$6,2,FALSE) -> 5 | O494: =IF(Requests[[#This Row],[Age (days)]]>Requests[[#This Row],[SLA Threshold]],"Yes","No") -> Yes
A495: RF5396393 | B495: 45696 | C495: 45774 | D495: Closed | E495: UNASSIGNED | F495: =IF(ISBLANK(C495), NETWORKDAYS(B495,TODAY()), NETWORKDAYS(B495,C495)) -> 55 | G495: CONFIGURATION MANAGEMENT | H495: SM Data Quality Discrepancy Report [Change Mgmt General]: GBL-C4 MARM PATIENT INSIGHTS SUPPORT | K495: DIGITAL CONFIGURATION MGMT, CI DATA QUALITY | L495: Digital | M495: =VLOOKUP(Requests[[#This Row],[Ticket ID]],[2]Requests!$A$2:$D$649,4,FALSE) -> 4 - Low | N495: =VLOOKUP(Requests[[#This Row],[Priority]],'SLA Config'!$B$3:$C$6,2,FALSE) -> 25 | O495: =IF(Requests[[#This Row],[Age (days)]]>Requests[[#This Row],[SLA Threshold]],"Yes","No") -> Yes
A496: RF5465991 | B496: 45737 | C496: 45745 | D496: Closed | E496: MALLIA04 | F496: =IF(ISBLANK(C496), NETWORKDAYS(B496,TODAY()), NETWORKDAYS(B496,C496)) -> 6 | G496: CHAMP | H496: Patient Insights - OSOT Deployment | K496: ANAND, ASHISH | L496: Support | M496: =VLOOKUP(Requests[[#This Row],[Ticket ID]],[2]Requests!$A$2:$D$649,4,FALSE) -> 2 - High | N496: =VLOOKUP(Requests[[#This Row],[Priority]],'SLA Config'!$B$3:$C$6,2,FALSE) -> 5 | O496: =IF(Requests[[#This Row],[Age (days)]]>Requests[[#This Row],[SLA Threshold]],"Yes","No") -> Yes
A497: RF5444915 | B497: 45726 | C497: 45745 | D497: Closed | E497: DURGAA02 | F497: =IF(ISBLANK(C497), NETWORKDAYS(B497,TODAY()), NETWORKDAYS(B497,C497)) -> 15 | G497: PASSPORT | H497: RM Fulfillment Ticket: Patient Insights - 20250307131059672 | K497: WAGNER, REBECCA | L497: Business | M497: =VLOOKUP(Requests[[#This Row],[Ticket ID]],[2]Requests!$A$2:$D$649,4,FALSE) -> 4 - Low | N497: =VLOOKUP(Requests[[#This Row],[Priority]],'SLA Config'!$B$3:$C$6,2,FALSE) -> 25 | O497: =IF(Requests[[#This Row],[Age (days)]]>Requests[[#This Row],[SLA Threshold]],"Yes","No") -> No
A498: RF5465198 | B498: 45737 | C498: 45742 | D498: Closed | E498: BABUS32 | F498: =IF(ISBLANK(C498), NETWORKDAYS(B498,TODAY()), NETWORKDAYS(B498,C498)) -> 4 | G498: PASSPORT | H498: Patient Insights | Dual Rfc to deploy changes related to new web application with OSOT KPI Review | UAT deployment | K498: BABU, SHRIDI | L498: Support | M498: =VLOOKUP(Requests[[#This Row],[Ticket ID]],[2]Requests!$A$2:$D$649,4,FALSE) -> 4 - Low | N498: =VLOOKUP(Requests[[#This Row],[Priority]],'SLA Config'!$B$3:$C$6,2,FALSE) -> 25 | O498: =IF(Requests[[#This Row],[Age (days)]]>Requests[[#This Row],[SLA Threshold]],"Yes","No") -> No
A499: RF5404791 | B499: 45701 | C499: 45754 | D499: Closed | E499: UNASSIGNED | F499: =IF(ISBLANK(C499), NETWORKDAYS(B499,TODAY()), NETWORKDAYS(B499,C499)) -> 38 | G499: CHAMP | H499: Patient Insights - Information/How-To | K499: TROUGHT, ALLISON | L499: Business | M499: =VLOOKUP(Requests[[#This Row],[Ticket ID]],[2]Requests!$A$2:$D$649,4,FALSE) -> 4 - Low | N499: =VLOOKUP(Requests[[#This Row],[Priority]],'SLA Config'!$B$3:$C$6,2,FALSE) -> 25 | O499: =IF(Requests[[#This Row],[Age (days)]]>Requests[[#This Row],[SLA Threshold]],"Yes","No") -> Yes
A500: RF5455492 | B500: 45733 | C500: 45741 | D500: Closed | E500: DURGAA02 | F500: =IF(ISBLANK(C500), NETWORKDAYS(B500,TODAY()), NETWORKDAYS(B500,C500)) -> 7 | G500: PASSPORT | H500: Patient Insights | New brand request for Kristen Verderber. | K500: DURGAM, AKHIL | L500: Support | M500: =VLOOKUP(Requests[[#This Row],[Ticket ID]],[2]Requests!$A$2:$D$649,4,FALSE) -> 4 - Low | N500: =VLOOKUP(Requests[[#This Row],[Priority]],'SLA Config'!$B$3:$C$6,2,FALSE) -> 25 | O500: =IF(Requests[[#This Row],[Age (days)]]>Requests[[#This Row],[SLA Threshold]],"Yes","No") -> No
A501: RF5405961 | B501: 45702 | C501: 45713 | D501: Closed | E501: BABUS32 | F501: =IF(ISBLANK(C501), NETWORKDAYS(B501,TODAY()), NETWORKDAYS(B501,C501)) -> 8 | G501: PASSPORT | H501: Patient Insights | Michael Shin | Passport and OPSA dashboards request | K501: WANG, ERIC | L501: Business | M501: =VLOOKUP(Requests[[#This Row],[Ticket ID]],[2]Requests!$A$2:$D$649,4,FALSE) -> 4 - Low | N501: =VLOOKUP(Requests[[#This Row],[Priority]],'SLA Config'!$B$3:$C$6,2,FALSE) -> 25 | O501: =IF(Requests[[#This Row],[Age (days)]]>Requests[[#This Row],[SLA Threshold]],"Yes","No") -> No
A502: RF5112393 | B502: 45518 | C502: 45740 | D502: Closed | E502: DINALK01 | F502: =IF(ISBLANK(C502), NETWORKDAYS(B502,TODAY()), NETWORKDAYS(B502,C502)) -> 159 | G502: PASSPORT | H502: Patient Insights - Enhancement Request - SPP Cohort | I502: Enhancement | J502: Tableau | K502: WANG, ERIC | L502: Business | M502: =VLOOKUP(Requests[[#This Row],[Ticket ID]],[2]Requests!$A$2:$D$649,4,FALSE) -> 3 - Medium | N502: =VLOOKUP(Requests[[#This Row],[Priority]],'SLA Config'!$B$3:$C$6,2,FALSE) -> 15 | O502: =IF(Requests[[#This Row],[Age (days)]]>Requests[[#This Row],[SLA Threshold]],"Yes","No") -> Yes
A503: RF5453320 | B503: 45730 | C503: 45740 | D503: Closed | E503: GUNDAP04 | F503: =IF(ISBLANK(C503), NETWORKDAYS(B503,TODAY()), NETWORKDAYS(B503,C503)) -> 7 | G503: PASSPORT | H503: Patient Insights New User request: Arooba Alam Marks | K503: WANG, ERIC | L503: Business | M503: =VLOOKUP(Requests[[#This Row],[Ticket ID]],[2]Requests!$A$2:$D$649,4,FALSE) -> 4 - Low | N503: =VLOOKUP(Requests[[#This Row],[Priority]],'SLA Config'!$B$3:$C$6,2,FALSE) -> 25 | O503: =IF(Requests[[#This Row],[Age (days)]]>Requests[[#This Row],[SLA Threshold]],"Yes","No") -> No
A504: RF5450650 | B504: 45728 | C504: 45740 | D504: Closed | E504: GUNDAP04 | F504: =IF(ISBLANK(C504), NETWORKDAYS(B504,TODAY()), NETWORKDAYS(B504,C504)) -> 9 | G504: PASSPORT | H504: RM Fulfillment Ticket: Patient Insights - 20250312155441414 | K504: GOLLER, MARK | L504: Business | M504: =VLOOKUP(Requests[[#This Row],[Ticket ID]],[2]Requests!$A$2:$D$649,4,FALSE) -> 4 - Low | N504: =VLOOKUP(Requests[[#This Row],[Priority]],'SLA Config'!$B$3:$C$6,2,FALSE) -> 25 | O504: =IF(Requests[[#This Row],[Age (days)]]>Requests[[#This Row],[SLA Threshold]],"Yes","No") -> No
A505: RF5432508 | B505: 45719 | C505: 45739 | D505: Closed | E505: UNASSIGNED | F505: =IF(ISBLANK(C505), NETWORKDAYS(B505,TODAY()), NETWORKDAYS(B505,C505)) -> 15 | G505: OTHER | H505: Access Request to CDW DB | K505: PATRO, P SAURAV KUMAR | L505: Digital | M505: =VLOOKUP(Requests[[#This Row],[Ticket ID]],[2]Requests!$A$2:$D$649,4,FALSE) -> 4 - Low | N505: =VLOOKUP(Requests[[#This Row],[Priority]],'SLA Config'!$B$3:$C$6,2,FALSE) -> 25 | O505: =IF(Requests[[#This Row],[Age (days)]]>Requests[[#This Row],[SLA Threshold]],"Yes","No") -> No
A506: RF5415271 | B506: 45708 | C506: 45738 | D506: Closed | E506: GUNDAP04 | F506: =IF(ISBLANK(C506), NETWORKDAYS(B506,TODAY()), NETWORKDAYS(B506,C506)) -> 22 | G506: PASSPORT | H506: Patient Insights | Tableau server upgrade - UAT | K506: PENG, XIAO JIANG | L506: Support | M506: =VLOOKUP(Requests[[#This Row],[Ticket ID]],[2]Requests!$A$2:$D$649,4,FALSE) -> 4 - Low | N506: =VLOOKUP(Requests[[#This Row],[Priority]],'SLA Config'!$B$3:$C$6,2,FALSE) -> 25 | O506: =IF(Requests[[#This Row],[Age (days)]]>Requests[[#This Row],[SLA Threshold]],"Yes","No") -> No
A507: RF5444468 | B507: 45726 | C507: 45738 | D507: Closed | E507: DURGAA02 | F507: =IF(ISBLANK(C507), NETWORKDAYS(B507,TODAY()), NETWORKDAYS(B507,C507)) -> 10 | G507: PASSPORT | H507: Patient Insights | Dual RFC to deploy Polaris customer engagement data into a table both UAT and Prod. | K507: DURGAM, AKHIL | L507: Support | M507: =VLOOKUP(Requests[[#This Row],[Ticket ID]],[2]Requests!$A$2:$D$649,4,FALSE) -> 4 - Low | N507: =VLOOKUP(Requests[[#This Row],[Priority]],'SLA Config'!$B$3:$C$6,2,FALSE) -> 25 | O507: =IF(Requests[[#This Row],[Age (days)]]>Requests[[#This Row],[SLA Threshold]],"Yes","No") -> No
A508: RF5449386 | B508: 45728 | C508: 45738 | D508: Closed | E508: DURGAA02 | F508: =IF(ISBLANK(C508), NETWORKDAYS(B508,TODAY()), NETWORKDAYS(B508,C508)) -> 8 | G508: PASSPORT | H508: Patient Insights | Dual RFC Created | To deploy changes related to Genotropin Data load in Prod environment | K508: DURGAM, AKHIL | L508: Support | M508: =VLOOKUP(Requests[[#This Row],[Ticket ID]],[2]Requests!$A$2:$D$649,4,FALSE) -> 4 - Low | N508: =VLOOKUP(Requests[[#This Row],[Priority]],'SLA Config'!$B$3:$C$6,2,FALSE) -> 25 | O508: =IF(Requests[[#This Row],[Age (days)]]>Requests[[#This Row],[SLA Threshold]],"Yes","No") -> No
A509: RF5374347 | B509: 45684 | C509: 45735 | D509: Closed | E509: GUNDAP04 | F509: =IF(ISBLANK(C509), NETWORKDAYS(B509,TODAY()), NETWORKDAYS(B509,C509)) -> 38 | G509: PASSPORT | H509: Patient Insight | Leave Behind Deck Extract - Q4 | K509: GUNDANNA, PUNYA | L509: Support | M509: =VLOOKUP(Requests[[#This Row],[Ticket ID]],[2]Requests!$A$2:$D$649,4,FALSE) -> 4 - Low | N509: =VLOOKUP(Requests[[#This Row],[Priority]],'SLA Config'!$B$3:$C$6,2,FALSE) -> 25 | O509: =IF(Requests[[#This Row],[Age (days)]]>Requests[[#This Row],[SLA Threshold]],"Yes","No") -> Yes
A510: RF5434705 | B510: 45720 | C510: 45735 | D510: Closed | E510: GUNDAP04 | F510: =IF(ISBLANK(C510), NETWORKDAYS(B510,TODAY()), NETWORKDAYS(B510,C510)) -> 12 | G510: PASSPORT | H510: Patient Insights | CDW table refresh to DEV and UAT | K510: GUNDANNA, PUNYA | L510: Support | M510: =VLOOKUP(Requests[[#This Row],[Ticket ID]],[2]Requests!$A$2:$D$649,4,FALSE) -> 4 - Low | N510: =VLOOKUP(Requests[[#This Row],[Priority]],'SLA Config'!$B$3:$C$6,2,FALSE) -> 25 | O510: =IF(Requests[[#This Row],[Age (days)]]>Requests[[#This Row],[SLA Threshold]],"Yes","No") -> No
A511: RF5435827 | B511: 45720 | C511: 45735 | D511: Closed | E511: GUNDAP04 | F511: =IF(ISBLANK(C511), NETWORKDAYS(B511,TODAY()), NETWORKDAYS(B511,C511)) -> 12 | G511: PASSPORT | H511: Patient Insights user access: Brian Goodman | K511: GUNDANNA, PUNYA | L511: Support | M511: =VLOOKUP(Requests[[#This Row],[Ticket ID]],[2]Requests!$A$2:$D$649,4,FALSE) -> 4 - Low | N511: =VLOOKUP(Requests[[#This Row],[Priority]],'SLA Config'!$B$3:$C$6,2,FALSE) -> 25 | O511: =IF(Requests[[#This Row],[Age (days)]]>Requests[[#This Row],[SLA Threshold]],"Yes","No") -> No
A512: RF5453321 | B512: 45730 | C512: 45735 | D512: Closed | E512: DURGAA02 | F512: =IF(ISBLANK(C512), NETWORKDAYS(B512,TODAY()), NETWORKDAYS(B512,C512)) -> 4 | G512: PASSPORT | H512: Patient Insights New User request: Arooba Alam Marks | K512: WANG, ERIC | L512: Business | M512: =VLOOKUP(Requests[[#This Row],[Ticket ID]],[2]Requests!$A$2:$D$649,4,FALSE) -> 4 - Low | N512: =VLOOKUP(Requests[[#This Row],[Priority]],'SLA Config'!$B$3:$C$6,2,FALSE) -> 25 | O512: =IF(Requests[[#This Row],[Age (days)]]>Requests[[#This Row],[SLA Threshold]],"Yes","No") -> No
A513: RF5435623 | B513: 45720 | C513: 45734 | D513: Closed | E513: DURGAA02 | F513: =IF(ISBLANK(C513), NETWORKDAYS(B513,TODAY()), NETWORKDAYS(B513,C513)) -> 11 | G513: PASSPORT | H513: Patient Insights | Dual RFC to deploy changes related to Vyndamax brand using BRE in the UAT / Prod environment. | K513: DURGAM, AKHIL | L513: Support | M513: =VLOOKUP(Requests[[#This Row],[Ticket ID]],[2]Requests!$A$2:$D$649,4,FALSE) -> 4 - Low | N513: =VLOOKUP(Requests[[#This Row],[Priority]],'SLA Config'!$B$3:$C$6,2,FALSE) -> 25 | O513: =IF(Requests[[#This Row],[Age (days)]]>Requests[[#This Row],[SLA Threshold]],"Yes","No") -> No
A514: RF5439830 | B514: 45722 | C514: 45734 | D514: Closed | E514: GUNDAP04 | F514: =IF(ISBLANK(C514), NETWORKDAYS(B514,TODAY()), NETWORKDAYS(B514,C514)) -> 9 | G514: PASSPORT | H514: Patient Insights | Patient Experience Dashboard issue | K514: WANG, ERIC | L514: Business | M514: =VLOOKUP(Requests[[#This Row],[Ticket ID]],[2]Requests!$A$2:$D$649,4,FALSE) -> 4 - Low | N514: =VLOOKUP(Requests[[#This Row],[Priority]],'SLA Config'!$B$3:$C$6,2,FALSE) -> 25 | O514: =IF(Requests[[#This Row],[Age (days)]]>Requests[[#This Row],[SLA Threshold]],"Yes","No") -> No
... A561: RF5483777 | B561: 45748 | C561: 45776 | D561: Closed | E561: GUNDAP04 | F561: =IF(ISBLANK(C561), NETWORKDAYS(B561,TODAY()), NETWORKDAYS(B561,C561)) -> 21 | G561: PASSPORT | H561: Transfer Time CVS | K561: DESAI, RAJ | L561: Business | M561: =VLOOKUP(Requests[[#This Row],[Ticket ID]],[2]Requests!$A$2:$D$649,4,FALSE) -> 4 - Low | N561: =VLOOKUP(Requests[[#This Row],[Priority]],'SLA Config'!$B$3:$C$6,2,FALSE) -> 25 | O561: =IF(Requests[[#This Row],[Age (days)]]>Requests[[#This Row],[SLA Threshold]],"Yes","No") -> No
A562: RF5484947 | B562: 45749 | D562: Pending Pfizer | E562: ANANDA40 | F562: =IF(ISBLANK(C562), NETWORKDAYS(B562,TODAY()), NETWORKDAYS(B562,C562)) -> 263 | G562: PASSPORT | H562: Patient Insights | looks like Caremark data for Lorbrena at least is not being captured by the dashboard: | K562: DESAI, RAJ | L562: Business | M562: =VLOOKUP(Requests[[#This Row],[Ticket ID]],[2]Requests!$A$2:$D$649,4,FALSE) -> 3 - Medium | N562: =VLOOKUP(Requests[[#This Row],[Priority]],'SLA Config'!$B$3:$C$6,2,FALSE) -> 15 | O562: =IF(Requests[[#This Row],[Age (days)]]>Requests[[#This Row],[SLA Threshold]],"Yes","No") -> Yes
A563: RF5486497 | B563: 45750 | C563: 45760 | D563: Closed | E563: BABUS32 | F563: =IF(ISBLANK(C563), NETWORKDAYS(B563,TODAY()), NETWORKDAYS(B563,C563)) -> 7 | G563: PASSPORT | H563: Patient Insights | user access request: PATIENTINSIGHTS-PROD-ONCOLOGYBRAND | K563: WANG, ERIC | L563: Business | M563: =VLOOKUP(Requests[[#This Row],[Ticket ID]],[2]Requests!$A$2:$D$649,4,FALSE) -> 4 - Low | N563: =VLOOKUP(Requests[[#This Row],[Priority]],'SLA Config'!$B$3:$C$6,2,FALSE) -> 25 | O563: =IF(Requests[[#This Row],[Age (days)]]>Requests[[#This Row],[SLA Threshold]],"Yes","No") -> No
A564: RF5486929 | B564: 45750 | D564: Work in progress | E564: MALLIA04 | F564: =IF(ISBLANK(C564), NETWORKDAYS(B564,TODAY()), NETWORKDAYS(B564,C564)) -> 262 | G564: PASSPORT | H564: Patient Insights | Python upgrade 3.8 to 3.11 | K564: DURGAM, AKHIL | L564: Support | M564: =VLOOKUP(Requests[[#This Row],[Ticket ID]],[2]Requests!$A$2:$D$649,4,FALSE) -> 4 - Low | N564: =VLOOKUP(Requests[[#This Row],[Priority]],'SLA Config'!$B$3:$C$6,2,FALSE) -> 25 | O564: =IF(Requests[[#This Row],[Age (days)]]>Requests[[#This Row],[SLA Threshold]],"Yes","No") -> Yes
A565: RF5487714 | B565: 45750 | C565: 45789 | D565: Closed | E565: GUNDAP04 | F565: =IF(ISBLANK(C565), NETWORKDAYS(B565,TODAY()), NETWORKDAYS(B565,C565)) -> 28 | G565: CHAMP | H565: Patient Insights -new service category of "Enhanced Service - Pharmacy Communications" | K565: TROUGHT, ALLISON | L565: Business | M565: =VLOOKUP(Requests[[#This Row],[Ticket ID]],[2]Requests!$A$2:$D$649,4,FALSE) -> 4 - Low | N565: =VLOOKUP(Requests[[#This Row],[Priority]],'SLA Config'!$B$3:$C$6,2,FALSE) -> 25 | O565: =IF(Requests[[#This Row],[Age (days)]]>Requests[[#This Row],[SLA Threshold]],"Yes","No") -> Yes
A566: RF5487849 | B566: 45750 | C566: 45759 | D566: Closed | E566: RAUTA20 | F566: =IF(ISBLANK(C566), NETWORKDAYS(B566,TODAY()), NETWORKDAYS(B566,C566)) -> 7 | G566: PASSPORT | H566: OPSA FRD Zip2Terr | K566: WANG, ERIC | L566: Business | M566: =VLOOKUP(Requests[[#This Row],[Ticket ID]],[2]Requests!$A$2:$D$649,4,FALSE) -> 3 - Medium | N566: =VLOOKUP(Requests[[#This Row],[Priority]],'SLA Config'!$B$3:$C$6,2,FALSE) -> 15 | O566: =IF(Requests[[#This Row],[Age (days)]]>Requests[[#This Row],[SLA Threshold]],"Yes","No") -> No
A567: RF5491757 | B567: 45754 | D567: Pending RFC | E567: MORES14 | F567: =IF(ISBLANK(C567), NETWORKDAYS(B567,TODAY()), NETWORKDAYS(B567,C567)) -> 260 | G567: PASSPORT | H567: Apply restrictions to SPP-level information for mentioned security groups in Brand Analytics dashboard | K567: WANG, ERIC | L567: Business | M567: =VLOOKUP(Requests[[#This Row],[Ticket ID]],[2]Requests!$A$2:$D$649,4,FALSE) -> 4 - Low | N567: =VLOOKUP(Requests[[#This Row],[Priority]],'SLA Config'!$B$3:$C$6,2,FALSE) -> 25 | O567: =IF(Requests[[#This Row],[Age (days)]]>Requests[[#This Row],[SLA Threshold]],"Yes","No") -> Yes
...

Sheet Problems
A1: Ticket ID | B1: Opened On | C1: Closed On | D1: Phase | E1: Assignee | F1: Age (days) | G1: Description | H1: Related Tickets | I1: Category | J1: Subcategory | K1: Requested By
A2: PM7003565 | B2: 44799 | C2: 44813 | D2: Closed | E2: SIRIVV02 | F2: =IF(ISBLANK(C2), TODAY() - B2, C2-B2) -> 14 | G2: Derm files -- we are receiving files with unexpected file name format . Opening this problem to track the issue. | I2: Interface Issue | J2: Interface Failure | K2: Support
A3: PM7003631 | B3: 44818 | C3: 44844 | D3: Closed | E3: SIRIVV02 | F3: =IF(ISBLANK(C3), TODAY() - B3, C3-B3) -> 26 | G3: DERM Job is getting failed daily(from 8-sep-2022) with the error "Invalid header in one of the derm files" | I3: Interface Issue | J3: Interface Failure | K3: Support
A4: PM7003681 | B4: 44830 | C4: 44834 | D4: Closed | E4: SIRIVV02 | F4: =IF(ISBLANK(C4), TODAY() - B4, C4-B4) -> 4 | G4: POT Files || We are receiving wrong files daily. Receiving files with mismatch dates in control file vs data files. This issue is recurring form 16th september. | I4: Interface Issue | J4: Interface Failure | K4: Support
A5: PM7003731 | B5: 44840 | C5: 44858 | D5: Closed | E5: SIRIVV02 | F5: =IF(ISBLANK(C5), TODAY() - B5, C5-B5) -> 18 | G5: POT files are diverted to Dev sever with an extra file 18+1 Hence IICS POT job in prod is failing | I5: Interface Issue | J5: Interface Failure | K5: Support
A6: PM7003914 | B6: 44887 | C6: 44908 | D6: Closed | E6: SIRIVV02 | F6: =IF(ISBLANK(C6), TODAY() - B6, C6-B6) -> 21 | G6: We are not receiving POT files before the scheduled time of IICS job | I6: Interface Issue | J6: Interface Failure | K6: Support
A7: PM7004937 | B7: 45076 | D7: Work in progress | E7: MALLIA04 | F7: =IF(ISBLANK(C7), TODAY() - B7, C7-B7) -> 1039 | G7: Champ master task flow is executing completely even when there are failures in subtasks, which is leading to load partial data/no data in dashboard | I7: Batch | J7: Interface Failure | K7: Support
A8: PM7004984 | B8: 45083 | C8: 45146 | D8: Closed | E8: MALLIA04 | F8: =IF(ISBLANK(C8), TODAY() - B8, C8-B8) -> 63 | G8: Patient insights support DL was not included in any of the incremental file load related jobs like DERM, POT & Bridge , These jobs feeds the data for Patient experience reports | I8: Batch | J8: IICS | K8: Support
A9: PM7005156 | B9: 45119 | C9: 45126 | D9: Closed | E9: SIRIVV02 | F9: =IF(ISBLANK(C9), TODAY() - B9, C9-B9) -> 7 | G9: DERM Job is getting failed from 7/4 as we are receiving new additional file called authorization file. | I9: Batch | J9: IICS | K9: Support
A10: PM7005215 | B10: 45128 | C10: 45146 | D10: Closed | E10: MALLIA04 | F10: =IF(ISBLANK(C10), TODAY() - B10, C10-B10) -> 18 | G10: Patient master taskflow is getting failed in production server after IICS R43 upgrade, Due to which the master patient job is getting failed and we need to trigger the job manually every time | I10: Batch | J10: IICS | K10: Support
A11: PM7005266 | B11: 45141 | C11: 45180 | D11: Closed | E11: DINALK01 | F11: =IF(ISBLANK(C11), TODAY() - B11, C11-B11) -> 39 | G11: Patient Insights | Fix non-conforming service accounts | I11: Audit | J11: Service Accounts | K11: Support
A12: PM7005291 | B12: 45146 | D12: Work in progress | E12: MALLIA04 | F12: =IF(ISBLANK(C12), TODAY() - B12, C12-B12) -> 969 | G12: Patient insights support DL was not included in any of the incremental file load related jobs like DERM, POT & Bridge , These jobs feeds the data for Patient experience reports | H12: PM7004984 | I12: Batch | J12: IICS | K12: Support
A13: PM7005349 | B13: 45160 | C13: 45313 | D13: Closed | E13: MALLIA04 | F13: =IF(ISBLANK(C13), TODAY() - B13, C13-B13) -> 153 | G13: Revoke Write access for Digital Patient Insights team from UAT environment | I13: User Access | J13: IICS | K13: Support
A14: PM7005524 | B14: 45191 | C14: 45232 | D14: Closed | E14: MALLIA04 | F14: =IF(ISBLANK(C14), TODAY() - B14, C14-B14) -> 41 | G14: Patient Insights | Copy control files from GBT HUB folder to GBT SPIF folder | I14: Interface Issue | J14: Interface Failure | K14: Support
A15: PM7005539 | B15: 45195 | C15: 45412 | D15: Closed | E15: DINALK01 | F15: =IF(ISBLANK(C15), TODAY() - B15, C15-B15) -> 217 | G15: Patient Insights | LASH | Multiple Patient ID tagged to 1 Case ID | I15: Data Issue | J15: LASH | K15: Support
A16: PM7005551 | B16: 45196 | C16: 45219 | D16: Closed | E16: ANANDA40 | F16: =IF(ISBLANK(C16), TODAY() - B16, C16-B16) -> 23 | G16: Patient Insights | GBT HUB | Control file name incorrect | I16: Interface Issue | J16: Interface Failure | K16: Support
A17: PM7005858 | B17: 45251 | C17: 45330 | D17: Closed | E17: BABUS32 | F17: =IF(ISBLANK(C17), TODAY() - B17, C17-B17) -> 79 | G17: Patient Insights | GitHub Dependabot alerts | I17: Environment | J17: GitHub | K17: Support
A18: PM7005892 | B18: 45258 | C18: 45279 | D18: Closed | E18: ANANDA40 | F18: =IF(ISBLANK(C18), TODAY() - B18, C18-B18) -> 21 | G18: Patient Insights | GBT HUB | Incorrect Control File | I18: Batch | J18: Interface Failure | K18: Support
A19: PM7006137 | B19: 45314 | C19: 45321 | D19: Closed | E19: GANJIR04 | F19: =IF(ISBLANK(C19), TODAY() - B19, C19-B19) -> 7 | G19: Patient Insights - CHAMP does not display the 2024 data | I19: Data Issue | J19: Tableau | K19: Support
A20: PM7006205 | B20: 45327 | D20: Work in progress | E20: ANANDA40 | F20: =IF(ISBLANK(C20), TODAY() - B20, C20-B20) -> 788 | G20: Patient Insights | Permanently fix IICS script failure for Tableau refresh | I20: Batch | J20: IICS | K20: Support
A21: PM7006215 | B21: 45329 | C21: 45369 | D21: Closed | E21: ANANDA40 | F21: =IF(ISBLANK(C21), TODAY() - B21, C21-B21) -> 40 | G21: Patient Insights | Fix Datasource Refresh Automatic Schdeule | I21: Batch | J21: IICS | K21: Support
A22: PM7006420 | B22: 45370 | D22: Work in progress | E22: MALLIA04 | F22: =IF(ISBLANK(C22), TODAY() - B22, C22-B22) -> 745 | G22: Biohaven IC Report data ingestion issue | S3 path inconsistency | I22: Batch | J22: IICS | K22: Support
A23: PM7006549 | B23: 45401 | C23: 45427 | D23: Closed | E23: MALLIA04 | F23: =IF(ISBLANK(C23), TODAY() - B23, C23-B23) -> 26 | G23: Patient Insights | Patient Experience data extract refresh and ETL job misalignment | I23: Batch | J23: IICS | K23: Support
A24: PM7006652 | B24: 45428 | C24: 45463 | D24: Closed | E24: ANANDA40 | F24: =IF(ISBLANK(C24), TODAY() - B24, C24-B24) -> 35 | G24: Patient Insight | 2 email for Job- Failure on Production | I24: Batch | J24: IICS | K24: Support
A25: PM7006689 | B25: 45434 | C25: 45527 | D25: Closed | E25: MALLIA04 | F25: =IF(ISBLANK(C25), TODAY() - B25, C25-B25) -> 93 | G25: Patient Insight: Automation of Job failures and Recommendation through Gen AI | I25: Batch | J25: IICS | K25: Support
A26: PM7006690 | B26: 45434 | C26: 45518 | D26: Closed | E26: MALLIA04 | F26: =IF(ISBLANK(C26), TODAY() - B26, C26-B26) -> 84 | G26: Patient Insight: Auto ticket assignment for Patient Insight Application | I26: Environment | J26: Service Manager | K26: Support
A27: PM7006691 | B27: 45434 | C27: 45477 | D27: Closed | E27: MALLIA04 | F27: =IF(ISBLANK(C27), TODAY() - B27, C27-B27) -> 43 | G27: Patient Insight: PAM alert | I27: Environment | J27: Monitoring | K27: Support
A28: PM7006728 | B28: 45441 | C28: 45446 | D28: Closed | E28: ANANDA40 | F28: =IF(ISBLANK(C28), TODAY() - B28, C28-B28) -> 5 | G28: Patient Insight | BHVN HCP Interface Failure | I28: Interface Issue | J28: Interface Failure | K28: Support
A29: PM7006922 | B29: 45476 | C29: 45490 | D29: Closed | E29: ANANDA40 | F29: =IF(ISBLANK(C29), TODAY() - B29, C29-B29) -> 14 | G29: Patient Insights | Set up notification process for GMFT jobs | I29: Environment | J29: Monitoring | K29: Support
A30: PM7006970 | B30: 45490 | D30: Work in progress | E30: BABUS32 | F30: =IF(ISBLANK(C30), TODAY() - B30, C30-B30) -> 625 | G30: Patient Insights | Dashboard access validation and streamline user access request | I30: User Access | J30: Report | K30: Support
A31: PM7007085 | B31: 45520 | C31: 45609 | D31: Closed | E31: BABUS32 | F31: =IF(ISBLANK(C31), TODAY() - B31, C31-B31) -> 89 | G31: Patient Insight | Fix GitHub vulnerabilities | I31: Environment | J31: Web App | K31: Support
A32: PM7007167 | B32: 45530 | D32: Work in progress | E32: MALLIA04 | F32: =IF(ISBLANK(C32), TODAY() - B32, C32-B32) -> 585 | G32: Patient Insights | Milliman Payer file notification missing | I32: Batch | J32: IICS | K32: Support
A33: PM7007244 | B33: 45545 | D33: Closed | E33: MALLIA04 | F33: =IF(ISBLANK(C33), TODAY() - B33, C33-B33) -> 570 | G33: Patient Insights | SPP V867 data issue | I33: Data Issue | J33: Tableau | K33: Support
A34: PM7007570 | B34: 45625 | C34: 45728 | D34: Closed | E34: ANANDA40 | F34: =IF(ISBLANK(C34), TODAY() - B34, C34-B34) -> 103 | G34: Patient Insights | Schedule Tableau Refresh | K34: Support
A35: PM7007724 | B35: 45664 | D35: Work in Progress | E35: ANANDA40 | F35: =IF(ISBLANK(C35), TODAY() - B35, C35-B35) -> 451 | G35: Patient Insights | TF_ES_Financial_load & TF_ES_Impact_Load - Data mismatch in specific columns | K35: Support
A36: PM7007836 | B36: 45694 | C36: 45728 | D36: Closed | E36: ANANDA40 | F36: =IF(ISBLANK(C36), TODAY() - B36, C36-B36) -> 34 | G36: Patient Insights | Remove GBT HUB from IICS monitoring | K36: Support
A37: PM7007899 | B37: 45713 | C37: 45728 | D37: Closed | E37: ANANDA40 | F37: =IF(ISBLANK(C37), TODAY() - B37, C37-B37) -> 15 | G37: Patient Insights | Job Failure in Production Envrionment (The root cause was escalated to the IICS Vendor and Network team, and the resolution involved stabilizing the job executions in production) | K37: Support
A38: PM7007952 | B38: 45721 | D38: Assign | E38: ANANDA40 | F38: =IF(ISBLANK(C38), TODAY() - B38, C38-B38) -> 394 | G38: Patient Insights | ES Intervention Mapping | K38: Support
A39: PM7007953 | B39: 45721 | D39: Assign | E39: ANANDA40 | F39: =IF(ISBLANK(C39), TODAY() - B39, C39-B39) -> 394 | G39: Patient Insights | ES Intervention Reason Mapping | K39: Support
A40: PM7007954 | B40: 45721 | D40: Work in Progress | E40: ANANDA40 | F40: =IF(ISBLANK(C40), TODAY() - B40, C40-B40) -> 394 | G40: Patient Insights | Velsipity I & I Load | K40: Support
A41: PM7007955 | B41: 45721 | D41: Assign | E41: ANANDA40 | F41: =IF(ISBLANK(C41), TODAY() - B41, C41-B41) -> 394 | G41: Patient Insights | Vyndamax Polaris Load | K41: Support
A42: PM7007956 | B42: 45721 | D42: Assign | E42: ANANDA40 | F42: =IF(ISBLANK(C42), TODAY() - B42, C42-B42) -> 394 | G42: Patient Insights | OSOT Monthly Load | K42: Support
A43: PM7007975 | B43: 45728 | D43: Work in Progress | E43: ANANDA40 | F43: =IF(ISBLANK(C43), TODAY() - B43, C43-B43) -> 387 | G43: Patient Insights | Automation of creation of user access list | K43: Support
A44: PM7008088 | B44: 45757 | D44: Assign | E44: ANANDA40 | F44: =IF(ISBLANK(C44), TODAY() - B44, C44-B44) -> 358 | G44: Patient Insights | Fix IICS meta data issue | K44: Support
A45: PM7007460 | B45: 45594 | C45: 45610 | D45: Closed | E45: GANJIR04 | F45: =IF(ISBLANK(C45), TODAY() - B45, C45-B45) -> 16 | G45: Patient Insights | PASS Site migration UAT testing | K45: Support
A46: PM7007712 | B46: 45659 | C46: 45733 | D46: Closed | E46: GUNDAP04 | F46: =IF(ISBLANK(C46), TODAY() - B46, C46-B46) -> 74 | G46: Patient Insights | Create new group for MASPA DTR users in all environments | K46: Support

Sheet (Hidden)
A1: Team | C1: Full Name | D1: Assignee
A2: All | C2: Kostas | D2: DINALK01
A3: Digital | C3: Anupama | D3: MALLIA04
A4: Business | C4: Vishnu | D4: SIRIVV02
A5: Project Team | C5: Ramesh | D5: GANJIR04
A6: Support | C6: Shridi | D6: BABUS32
C7: Ashish | D7: ANANDA40
C8: Punya | D8: GUNDAP04
C9: Uma | D9: CHANDU06
